Workbook

Sheet Read Me
A1: Foundation Scoping Record — Northstar Demo
A2: Internal commercial/scoping record. Foundation Scoping determines how an already-established strategy should be implemented. It is narrower than Blueprint and does not recreate strategy.
A4: Purpose | B4: Translate an approved strategic foundation into implementation scope, responsibilities, complexity, delivery economics, and a human-reviewable fixed-price recommendation.
A5: When used | B5: Direct-to-Foundation when strategy is already sufficiently established, or as the implementation/commercial scoping record after an approved Blueprint when a fixed Foundation scope still needs to be priced.
A6: Demo boundary | B6: Northstar previously served as the Blueprint demonstration. This workbook assumes the strategic direction is now approved and uses the full-scope Foundation scenario for illustration. It does not rewrite the prior Diagnostic route.
A7: Important boundary | B7: Foundation Scoping answers how approved strategy should be implemented. Material strategic unknowns route back to strategic review rather than being quietly resolved here.
A8: Pricing boundary | B8: Complexity, reference value, and delivery economics must validate one another. AI may calculate and recommend. All Foundation pricing requires human approval.
A9: Client-facing boundary | B9: The client normally receives one fixed Foundation investment. Complexity score, internal pricing band, reference values, labor cost, gross margin, and AI confidence remain internal.
A11: Core rules
A12: FOUNDATION_SCOPING != BLUEPRINT
A13: IMPLEMENTATION_UNKNOWN != STRATEGIC_UNKNOWN
A14: COMPLEXITY → REFERENCE VALUE → DELIVERY ECONOMICS
A15: AI_RECOMMENDATION != HUMAN_PRICE_APPROVAL
A16: CLIENT_FACING_PRICE = ONE_FIXED_INVESTMENT
A17: INTERNAL_ECONOMICS_MUST_NOT_APPEAR_IN_PROPOSAL

Sheet Scoping Summary
A1: Scoping Summary
A2: Internal executive view of implementation context, scope state, complexity, and commercial readiness.
A4: Field | B4: Current Demo State | C4: Status | D4: Source / Basis | E4: Owner | F4: Decision / Action | G4: Client-Facing?
A5: Entry Path | B5: Approved Blueprint → Foundation Scoping | C5: DEMO ASSUMPTION | D5: Northstar demo sequence | E5: Strategist | F5: Use approved Blueprint as strategic source. | G5: No
A6: Business Objective | B6: Increase qualified corporate leadership conversations and improve visibility into marketing contribution. | C6: APPROVED FOR DEMO | D6: Approved Blueprint scenario | E6: Client + Strategist | F6: Preserve through implementation. | G6: Yes
A7: Website Objective | B7: Support corporate buyer evaluation, proof, routing, and meaningful conversion while retaining individual learner path. | C7: APPROVED FOR DEMO | D7: Approved Blueprint scenario | E7: Strategist | F7: Preserve through architecture and UX. | G7: Yes
A8: Primary Buyer | B8: Corporate leadership / sales / L&D decision-makers; individual professionals secondary. | C8: APPROVED FOR DEMO | D8: Approved Blueprint scenario | E8: Strategist | F8: Use for page roles and CTA logic. | G8: Yes
A9: Implementation Variant | B9: Full custom SimpliFoundation | C9: DEMO ASSUMPTION | D9: Full-scope proposal scenario | E9: Commercial Lead | F9: Validate final scope before pricing. | G9: Yes
A10: Strategic Unknowns | B10: None assumed material for demo. | C10: HUMAN REVIEW | D10: Must be validated before Foundation bypass / activation. | E10: Strategist | F10: Escalate any material strategic unknown. | G10: No
A11: Implementation Unknowns | B11: Final page count, component count, migration volume, exact integrations, final event taxonomy, final stakeholder cadence. | C11: OPEN | D11: Scoping inputs incomplete | E11: Project Lead | F11: Resolve before fixed-price approval where material. | G11: No
A12: Complexity Score | B12: See Complexity Score tab. | C12: FORMULA | E12: Commercial Lead | F12: Validate scored assumptions. | G12: No
A13: Reference Value | B13: See Deliverable Validation tab. | C13: FORMULA / INTERNAL | E13: Commercial Lead | F13: Validate included deliverables. | G13: No
A14: Delivery Economics | B14: See Delivery Economics tab. | C14: INCOMPLETE | E14: Commercial Lead | F14: Populate current role/cost assumptions. | G14: No
A15: Recommended Fixed Investment | B15: See Pricing Recommendation tab. | C15: BLOCKED UNTIL ECONOMICS + HUMAN APPROVAL | E15: Commercial Approver | F15: Approve one fixed investment. | G15: Yes

Sheet Strategic Foundation
A1: Strategic Foundation Validation
A2: This tab confirms whether strategy is sufficient for Foundation. It does not redevelop strategy.
A4: Strategic Input | B4: Required State | C4: Demo State | D4: Status | E4: Evidence / Source | F4: Remaining Unknown | G4: Action
A5: Business Objective | B5: Approved | C5: Qualified corporate growth + clearer marketing contribution. | D5: APPROVED FOR DEMO | E5: Approved Blueprint scenario | G5: Preserve
A6: Website Objective | B6: Approved | C6: Support evaluation, proof, routing, conversion, and measurement. | D6: APPROVED FOR DEMO | E6: Approved Blueprint scenario | G6: Preserve
A7: ICP / Primary Buyers | B7: Approved | C7: Corporate decision-makers primary; individual learner secondary. | D7: APPROVED FOR DEMO | E7: Approved Blueprint scenario | G7: Preserve
A8: Positioning | B8: Sufficiently established | C8: Executive learning partner with faculty depth, customization, business relevance, and enterprise credibility. | D8: APPROVED FOR DEMO | E8: Approved Blueprint scenario | G8: Preserve
A9: Differentiation / UVP | B9: Sufficiently established | C9: Differentiation is stronger in sales conversation than current digital experience. | D9: APPROVED FOR DEMO | E9: Approved Blueprint scenario | G9: Translate into proof + messaging
A10: Core Offers | B10: Defined | C10: Corporate programs + individual/seminar pathways. | D10: APPROVED FOR DEMO | E10: Approved Blueprint scenario | F10: Exact product inventory for final architecture. | G10: Implementation detail
A11: Messaging Direction | B11: Sufficiently established | C11: Corporate-first, proof-aware, decision-supporting narrative. | D11: APPROVED FOR DEMO | E11: Approved Blueprint scenario | G11: Preserve
A12: Buyer Journey | B12: Sufficiently established | C12: Awareness/evaluation occurs across referrals, events, PR, faculty visibility, social/content, then website evaluation. | D12: APPROVED FOR DEMO | E12: Approved Blueprint scenario | F12: Final page-by-page routing. | G12: Implementation detail
A13: Conversion Objectives | B13: Defined | C13: Qualified corporate consultation + lower-friction supporting paths. | D13: APPROVED FOR DEMO | E13: Approved Blueprint scenario | F13: Final form/CRM fields. | G13: Implementation detail
A14: Success Criteria | B14: Defined enough to scope | C14: Meaningful buyer progression + more trustworthy measurement. | D14: APPROVED FOR DEMO | E14: Approved Blueprint scenario | F14: Exact post-launch baseline and targets. | G14: Implementation detail
A15: Material Strategic Unknowns | B15: None that would materially change implementation scope | C15: None assumed for demo. | D15: HUMAN REVIEW | E15: Requires strategist confirmation before pricing. | F15: If discovered, route back to strategic review. | G15: Gate

Sheet Implementation Scope
A1: Implementation Scope
A2: Full-scope demo of Foundation implementation requirements. Human review determines the final SOW.
A4: Workstream | B4: In Scope? | C4: Implementation Requirement | D4: Known Quantity / Level | E4: Open Scoping Question | F4: Client Responsibility | G4: SimpliCreative Responsibility | H4: Status | I4: Strategic Impact if Changed
A5: Messaging & Editorial | B5: Yes | C5: Website Messaging & Content Blueprint, Brand Voice & Editorial Guide, claim/evidence controls, page-level messaging. | D5: Meaningful development | E5: What existing messaging assets are already approved? | F5: Provide current materials, proof, approvals. | G5: Lead development, synthesis, drafting, review. | H5: DEMO ASSUMPTION | I5: High
A6: Information Architecture | B6: Yes | C6: Integrated site architecture, navigation, buyer intent, URLs, redirects, metadata/schema. | D6: Multiple journeys/templates | E6: Final page inventory and retirement/migration count? | F6: Approve architecture and URL changes. | G6: Lead architecture and integrated workbook. | H6: DEMO ASSUMPTION | I6: High
A7: Website Content | B7: Yes | C7: Page briefs, production copy, proof placement, CTA logic, editorial review. | D7: Significant work | E7: Final page/template count and content reuse? | F7: Provide SME access, proof, timely approvals. | G7: Draft/edit approved website content. | H7: OPEN | I7: High
A8: UX / Conversion | B8: Yes | C8: Corporate-first routing, individual path, CTA hierarchy, forms, qualification logic. | D8: Multiple paths | E8: Exact lower-friction conversion tools? | F8: Validate sales/CRM requirements. | G8: Lead UX/conversion requirements. | H8: OPEN | I8: High
A9: Custom Visual Design | B9: Yes | C9: Custom homepage, core templates, reusable components, responsive experience. | D9: Larger/custom | E9: How many unique core templates/components? | F9: Approve design direction. | G9: Lead design system and page/template design. | H9: OPEN | I9: Medium
A10: WordPress Development | B10: Yes | C10: Custom WP implementation, reusable component system, marketer-safe controls. | D10: Advanced custom | E10: Hosting/technical constraints? | F10: Provide access and technical requirements. | G10: Build/configure approved implementation. | H10: OPEN | I10: Medium
A11: Forms & CRM | B11: Yes | C11: Consultation/qualification forms, source context, routing, CRM integration. | D11: Multiple workflows | E11: Exact fields, lifecycle stages, routing rules? | F11: Provide HubSpot/process ownership. | G11: Implement approved forms/integration. | H11: OPEN | I11: High
A12: Analytics & Measurement | B12: Yes | C12: GA4/GTM, custom events/funnels, conversion tracking, baseline/reporting setup. | D12: Custom events/funnels | E12: Current property/container health and event taxonomy? | F12: Provide access and reporting needs. | G12: Implement/validate measurement. | H12: OPEN | I12: High
A13: SEO | B13: Yes | C13: Metadata, internal linking, on-page SEO, crawl/indexing, migration protection. | D13: Significant | E13: Current ranking/URL equity priorities? | F13: Provide Search Console/access. | G13: Implement approved SEO architecture. | H13: OPEN | I13: Medium
A14: AEO / GEO | B14: Yes | C14: Entity clarity, answer-focused content, authority cues, structured content. | D14: Significant | E14: Priority AI/recommendation research themes? | F14: Provide SME/proof context. | G14: Implement approved AEO/GEO requirements. | H14: OPEN | I14: Medium
A15: Schema | B15: Yes | C15: Page-specific schema where actual content supports it. | D15: Multiple types | E15: Final page eligibility? | F15: Provide accurate factual/entity data. | G15: Implement valid structured data. | H15: OPEN | I15: Low
... A20: QA / Launch | B20: Yes | C20: Strategic Fidelity QA, Technical QA, launch, live validation, handoff. | D20: Full | E20: Approved browser/device/QA scope? | F20: Participate in final approvals. | G20: Lead QA/launch documentation. | H20: OPEN | I20: Medium

Sheet Responsibility Map
A1: Responsibility Map
A2: Clarifies client, SimpliCreative, and partner ownership before scope and price are approved.
A4: Area | B4: SimpliCreative | C4: Northstar | D4: Existing / Other Partner | E4: Decision Needed | F4: Status | G4: Commercial Impact
A5: Strategy | B5: Implement approved strategy; escalate material strategic gaps. | C5: Approve material changes. | D5: None assumed. | E5: Confirm strategic approver. | F5: OPEN | G5: High
A6: Content | B6: Draft/edit agreed website copy and page requirements. | C6: Provide proof, SMEs, factual review, approvals. | D6: Potential internal content owner. | E6: Confirm page/content ownership split. | F6: OPEN | G6: High
A7: Design | B7: Lead approved custom UX/visual design. | C7: Review/approve. | D7: None assumed. | E7: Confirm stakeholder review group. | F7: OPEN | G7: Medium
A8: Development | B8: Build/configure approved WordPress experience. | C8: Provide access / infrastructure decisions. | D8: Hosting/IT may participate. | E8: Confirm hosting/IT owner. | F8: OPEN | G8: Medium
A9: CRM / MarTech | B9: Implement agreed forms/integrations. | C9: Own CRM governance and sales process. | D9: HubSpot admin/partner TBD. | E9: Confirm technical owner and responsibilities. | F9: OPEN | G9: High
A10: Analytics | B10: Implement approved web tracking. | C10: Own business process/data discipline. | D10: Existing analytics support TBD. | E10: Confirm ongoing reporting owner. | F10: OPEN | G10: Medium
A11: SEO/AEO/GEO | B11: Implement approved discoverability requirements. | C11: Provide expertise/proof/content approvals. | D11: Existing SEO partner TBD. | E11: Confirm overlap / handoff if partner exists. | F11: OPEN | G11: Medium
A12: Migration | B12: Plan/execute approved migration. | C12: Decide retain/retire/archive and provide content. | D12: IT/content partner TBD. | E12: Confirm migration support. | F12: OPEN | G12: Medium
A13: Launch | B13: Lead deployment/QA within approved technical scope. | C13: Authorize launch and approve final state. | D13: Hosting/IT may assist. | E13: Confirm launch authority. | F13: OPEN | G13: High

Sheet Dependencies & Risks
A1: Dependencies & Risks
A2: Material scope, delivery, and pricing dependencies that must be resolved or explicitly accepted.
A4: ID | B4: Dependency / Risk | C4: Type | D4: Impact if Unresolved | E4: Owner | F4: Required Resolution | G4: Status | H4: Pricing / Scope Effect
A5: DR-001 | B5: Final page / template inventory | C5: Scope dependency | D5: Copy, design, dev, migration, and QA volume remain uncertain. | E5: Strategist + Client | F5: Approve architecture scope. | G5: OPEN | H5: Potential material
A6: DR-002 | B6: Migration volume | C6: Delivery dependency | D6: Content migration effort cannot be estimated reliably. | E6: Client + Project Lead | F6: Inventory current content/files. | G6: OPEN | H6: Potential material
A7: DR-003 | B7: HubSpot workflows / lifecycle | C7: Integration dependency | D7: CRM scope and measurement complexity remain uncertain. | E7: Client CRM Owner | F7: Document current state and target requirements. | G7: OPEN | H7: Material
A8: DR-004 | B8: Final analytics event taxonomy | C8: Measurement dependency | D8: Build and QA effort remain uncertain. | E8: Measurement Owner | F8: Approve events/funnels. | G8: OPEN | H8: Moderate
A9: DR-005 | B9: Proof / claim permissions | C9: Content dependency | D9: Copy and proof modules may need rework if evidence is unavailable. | E9: Client | F9: Provide approved evidence/permissions. | G9: OPEN | H9: Moderate
A10: DR-006 | B10: Custom APIs / ERP | C10: Technical risk | D10: Could move integrations from standard to complex. | E10: Client IT | F10: Confirm whether any custom API/ERP work is required. | G10: OPEN | H10: Automatic human review
A11: DR-007 | B11: Stakeholder count / governance | C11: Governance risk | D11: More than five active stakeholders triggers review. | E11: Project Lead | F11: Confirm active approvers/reviewers. | G11: OPEN | H11: Potential material
A12: DR-008 | B12: Timeline pressure | C12: Delivery risk | D12: Compressed schedule can increase delivery cost/risk. | E12: Client + Project Lead | F12: Confirm desired launch window. | G12: OPEN | H12: Potential material
A13: DR-009 | B13: Accessibility requirements | C13: Compliance / scope risk | D13: Higher-complexity requirements may expand remediation/testing. | E13: Client | F13: Confirm required standard/regulatory context. | G13: OPEN | H13: Potential material

Sheet Complexity Score
A1: Foundation Complexity Score
A2: 15-dimension internal score. Demo inputs are illustrative assumptions and require human validation.
A4: Dimension | B4: Simple (1) | C4: Moderate (2) | D4: Complex (3) | E4: Demo Score | F4: Demo Basis | G4: Human Review
A5: Storytelling & Messaging | B5: Apply/refine | C5: Meaningful development | D5: Major strategic development | E5: 2 | F5: Meaningful development assumed; strategy already approved. | G5: REVIEW
A6: Information Architecture | B6: Straightforward | C6: Multiple journeys/templates | D6: Complex architecture | E6: 2 | F6: Corporate + individual paths and multiple templates. | G6: REVIEW
A7: Content | B7: Mostly ready | C7: Significant work/migration | D7: Extensive creation/migration | E7: 3 | F7: Full-scope demo assumes significant creation + extensive migration. | G7: REVIEW
A8: Design System | B8: Standard | C8: Larger/custom | D8: Advanced/custom | E8: 2 | F8: Custom design system assumed. | G8: REVIEW
A9: CMS | B9: Standard | C9: Complex structures | D9: Advanced workflows/data | E9: 3 | F9: Advanced custom component/CMS system assumed. | G9: REVIEW
A10: Conversion | B10: Straightforward | C10: Multiple paths | D10: Complex routing/qualification | E10: 2 | F10: Corporate + individual + assessment/guarantee paths. | G10: REVIEW
A11: CRM / MarTech | B11: Standard | C11: Multiple workflows | D11: Significant architecture | E11: 3 | F11: HubSpot workflows and routing are meaningful unknowns. | G11: REVIEW
A12: Analytics | B12: Standard | C12: Custom events/funnels | D12: Cross-system measurement | E12: 3 | F12: Custom events + CRM opportunity linkage. | G12: REVIEW
A13: SEO/AEO/GEO | B13: Foundational | C13: Significant | D13: Broad/complex | E13: 2 | F13: Significant implementation across full architecture. | G13: REVIEW
A14: Accessibility | B14: Standard | C14: Meaningful remediation | D14: High-complexity requirements | E14: 2 | F14: Meaningful remediation assumed; no special regulatory scope yet. | G14: REVIEW
A15: Integrations | B15: Few/standard | C15: Several | D15: API/ERP/custom | E15: 2 | F15: Several integrations assumed; API/ERP unresolved. | G15: REVIEW
A16: Stakeholders | B16: 1–2 | C16: 3–5 | D16: Multiple departments | E16: 2 | F16: Cross-functional approval group assumed. | G16: REVIEW
... A19: Partner Coordination | B19: Minimal | C19: 1–2 partners | D19: Multiple partners | E19: 2 | F19: Potential hosting/IT/CRM/SEO coordination. | G19: REVIEW
A20: TOTAL COMPLEXITY SCORE | E20: =SUM(E5:E19)
A21: CLASSIFICATION | E21: =IF(E20<=21,"Core",IF(E20<=30,"Standard",IF(E20<=38,"Growth","Complex")))
A22: INTERNAL PRICING BAND | E22: =IF(E20<=21,"$35K–$45K",IF(E20<=30,"$45K–$65K",IF(E20<=38,"$65K–$85K","$85K–$100K+")))

Sheet Deliverable Validation
A1: Deliverable Reference-Value Validation
A2: Internal validation only. Reference values do not make Foundation an à la carte menu and do not appear in client proposals.
A4: Deliverable / Workstream | B4: Included? | C4: Internal Reference Value | D4: Qty | E4: Extended Reference Value | F4: Notes | G4: Review
A5: Storytelling & Messaging Architecture | B5: Yes | C5: 7500 | D5: 1 | E5: =IF(B5="Yes",C5*D5,0) | F5: Bundled / custom | G5: REVIEW
A6: Positioning / UVP refinement | B6: No | C6: 5000 | D6: 0 | E6: =IF(B6="Yes",C6*D6,0) | F6: Not assumed necessary after approved Blueprint. | G6: REVIEW
A7: Website Strategy + IA | B7: Yes | C7: 5000 | D7: 1 | E7: =IF(B7="Yes",C7*D7,0) | F7: Integrated architecture included. | G7: REVIEW
A8: Buyer Journey / Conversion Architecture | B8: Yes | C8: 4000 | D8: 1 | E8: =IF(B8="Yes",C8*D8,0) | F8: Multiple buyer paths. | G8: REVIEW
A9: AEO / AI Recommendation Strategy | B9: Yes | C9: 4000 | D9: 1 | E9: =IF(B9="Yes",C9*D9,0) | F9: Foundation implementation context. | G9: REVIEW
A10: SEO / Discoverability Architecture | B10: Yes | C10: 4000 | D10: 1 | E10: =IF(B10="Yes",C10*D10,0) | F10: Foundation implementation context. | G10: REVIEW
A11: Measurement Architecture | B11: Yes | C11: 3500 | D11: 1 | E11: =IF(B11="Yes",C11*D11,0) | F11: Measurement / CRM design. | G11: REVIEW
A12: Custom Homepage UX + Design | B12: Yes | C12: 6000 | D12: 1 | E12: =IF(B12="Yes",C12*D12,0) | F12: Custom homepage. | G12: REVIEW
A13: Custom Core Page Template | B13: Yes | C13: 2500 | D13: 4 | E13: =IF(B13="Yes",C13*D13,0) | F13: Illustrative quantity; human review. | G13: REVIEW
A14: Secondary/Reused Page Layout | B14: Yes | C14: 1000 | D14: 8 | E14: =IF(B14="Yes",C14*D14,0) | F14: Illustrative quantity; human review. | G14: REVIEW
A15: Custom Landing Page | B15: No | C15: 2500 | D15: 0 | E15: =IF(B15="Yes",C15*D15,0) | F15: Not assumed unless campaign-specific need emerges. | G15: REVIEW
A16: WordPress Development Foundation | B16: Yes | C16: 10000 | D16: 1 | E16: =IF(B16="Yes",C16*D16,0) | F16: Bundled development foundation. | G16: REVIEW
... A31: Additional Migration | B31: Yes | C31: 125 | D31: 40 | E31: =IF(B31="Yes",C31*D31,0) | F31: Illustrative additional pages; human review. | G31: REVIEW
A32: TOTAL INTERNAL REFERENCE VALUE | E32: =SUM(E5:E31)

Sheet Delivery Economics
A1: Delivery Economics
A2: Internal cost and margin validation. Blue cells are human/commercial inputs. Do not expose this tab in client-facing proposals.
A4: Role / Cost | B4: Estimated Hours / Qty | C4: Loaded Rate / Unit Cost | D4: Extended Cost | E4: Source / Basis | F4: Status | G4: Notes
A5: Strategist / Account Lead | D5: =IF(OR(B5="",C5=""),0,B5*C5) | E5: Current internal labor model required | F5: PENDING
A6: Content / Messaging | D6: =IF(OR(B6="",C6=""),0,B6*C6) | E6: Current internal labor model required | F6: PENDING
A7: UX / Design | D7: =IF(OR(B7="",C7=""),0,B7*C7) | E7: Current internal labor model required | F7: PENDING
A8: Development | D8: =IF(OR(B8="",C8=""),0,B8*C8) | E8: Current internal labor model required | F8: PENDING
A9: SEO / AEO / Analytics | D9: =IF(OR(B9="",C9=""),0,B9*C9) | E9: Current internal labor model required | F9: PENDING
A10: Project Management / QA | D10: =IF(OR(B10="",C10=""),0,B10*C10) | E10: Current internal labor model required | F10: PENDING
A11: Contractors | D11: =IF(OR(B11="",C11=""),0,B11*C11) | E11: Current contractor quotes / assumptions | F11: PENDING
A12: Software / Project Expenses | D12: =IF(OR(B12="",C12=""),0,B12*C12) | E12: Project-specific costs | F12: PENDING
A13: SUBTOTAL DELIVERY COST | D13: =SUM(D5:D12)
A14: CONTINGENCY %
A15: RISK-ADJUSTED DELIVERY COST | D15: =D13*(1+B14)

Sheet Pricing Recommendation
A1: Foundation Pricing Recommendation
A2: Complexity, reference value, and delivery economics must validate one another before one fixed investment is recommended.
A4: Control | B4: Value | C4: Status | D4: Interpretation | E4: Human Decision | F4: Client-Facing?
A5: Complexity Score | B5: ='Complexity Score'!E20 | C5: FORMULA | D5: Internal complexity signal. | F5: No
A6: Complexity Classification | B6: ='Complexity Score'!E21 | C6: FORMULA | D6: Internal classification. | F6: No
A7: Internal Pricing Band | B7: ='Complexity Score'!E22 | C7: FORMULA | D7: Guardrail, not client price. | F7: No
A8: Deliverable Reference Value | B8: ='Deliverable Validation'!E32 | C8: FORMULA | D8: Validates scope/responsibility; not line-item client pricing. | F8: No
A9: Risk-Adjusted Delivery Cost | B9: ='Delivery Economics'!D15 | C9: BLOCKED UNTIL INPUTS | D9: Delivery economics cannot validate price until costs are populated. | F9: No
A10: Approved Margin Floor | C10: HUMAN INPUT | D10: Current commercial policy required. | F10: No
A11: Margin-Supporting Minimum Price | B11: =IF(OR(B9="",B10=""),"",B9/(1-B10)) | C11: FORMULA AFTER INPUT | D11: Price needed to meet approved margin floor. | F11: No
A12: Recommended Fixed Investment | C12: BLOCKED | D12: AI may recommend only after all three controls reconcile. | F12: Yes
A13: Pricing Review Result | C13: BLOCKED | D13: PASS / PRICING REVIEW REQUIRED. | F13: No
A14: Human Approver | C14: PENDING | D14: All Foundation pricing requires human approval. | F14: No
A15: Final Approved Price | C15: PENDING | D15: One client-facing fixed investment. | F15: Yes

Sheet Approval Gate
A1: Foundation Scoping Approval Gate
A2: Foundation cannot move to a final proposal until material scoping and commercial gates are approved.
A4: Gate | B4: Required State | C4: Demo State | D4: Status | E4: Owner | F4: Evidence / Decision | G4: Blocks Proposal?
A5: Strategic Foundation | B5: No unresolved material strategic unknowns. | C5: Human review required. | D5: PENDING | E5: Strategist | G5: Yes
A6: Implementation Scope | B6: Required deliverables and responsibilities sufficiently defined. | C6: Several open quantities/dependencies. | D6: PENDING | E6: Project Lead + Specialists | G6: Yes
A7: Architecture / Content Volume | B7: Page/template/migration scope understood enough to price. | C7: Not finalized in demo. | D7: PENDING | E7: Strategist + Content Lead | G7: Yes
A8: Technical / Integration Scope | B8: CMS, CRM, forms, integrations, accessibility, migration, performance understood enough to price. | C8: Several open items. | D8: PENDING | E8: Technical Lead | G8: Yes
A9: Stakeholders / Partners | B9: Active approvers and partner responsibilities defined. | C9: Open. | D9: PENDING | E9: Project Lead | G9: Yes
A10: Timeline | B10: Delivery window sufficiently known. | C10: Open. | D10: PENDING | E10: Project Lead + Client | G10: Yes
A11: Complexity Score | B11: Human-reviewed scoring complete. | C11: Demo assumptions only. | D11: PENDING | E11: Commercial Lead | G11: Yes
A12: Reference Value | B12: Included deliverables/quantities human-reviewed. | C12: Demo assumptions only. | D12: PENDING | E12: Commercial Lead | G12: Yes
A13: Delivery Economics | B13: Hours/costs/contingency populated. | C13: Not populated. | D13: BLOCKED | E13: Commercial Lead | G13: Yes
A14: Margin Validation | B14: Approved margin floor passes. | C14: Cannot calculate yet. | D14: BLOCKED | E14: Commercial Approver | G14: Yes
A15: Fixed Investment | B15: One price recommended and approved. | C15: Not available. | D15: BLOCKED | E15: Authorized Human | G15: Yes
A16: Proposal Ready | B16: All required gates above approved. | C16: No. | D16: BLOCKED | E16: Commercial Approver | G16: Yes

Sheet Change Log
A1: Change Log
A2: Revision history for the Foundation Scoping Record.
A4: Version | B4: Date | C4: Requested By | D4: Area | E4: Change | F4: Status | G4: Approved By
A5: v1.0 | B5: 2026-09-03 | C5: SimpliCreative | D5: All | E5: Initial Gold Standard created for Northstar full-scope Foundation scoping demonstration. Complexity/reference-value assumptions are illustrative; delivery economics and fixed price intentionally remain unresolved. | F5: Issued for Human Review
