Workbook

Sheet Read Me
A1: NuVue — Integrated Site Architecture
A2: Gold-standard Foundation workbook combining page architecture, buyer intent, metadata, schema, redirects, navigation, proof dependencies, and measurement.
A4: What this is | B4: The page-level source of truth for the proposed NuVue website architecture. It consolidates the prior Proposed Site Architecture workbook and the separate Meta & Schema Recommendations workbook into one governed implementation artifact.
A5: Why it exists | B5: Copy, design, development, SEO, AEO/GEO, analytics, and migration should not rely on disconnected page lists. Each material page should carry its purpose, buyer intent, CTA, URL, metadata, schema, dependencies, and measurement context in one place.
A6: Main tab | B6: Sitemap is the page-level source of truth. Filter by Status, Buyer Intent, Section, Schema, Review Flag, or Redirect Requirement.
A7: Buyer intent | B7: Buyer intent is a planning input, not a rigid page taxonomy. Intent fields marked TBD or Draft require human review before approval.
A8: Metadata | B8: Meta title and description live on the Sitemap row for each page. Character counts use formulas. Strategic pages are populated from the NuVue Meta & Schema Recommendations source; other rows remain blank until researched and reviewed.
A9: Schema | B9: Schema types must match actual page content. A blank schema cell is a content/research gap, not permission for AI to invent eligibility.
A10: Redirects | B10: Redirects are generated from existing vs. proposed URLs where a clear change exists. Retired pages remain unresolved until a human approves the destination.
A11: Navigation | B11: Navigation tab carries the current proposed NuVue navigation context. It is supporting architecture, not a replacement for the Sitemap tab.
A12: Approval | B12: This demo workbook is DRAFT / HUMAN REVIEW. Proposed page, URL, intent, metadata, schema, redirect, or proof decisions do not become implementation requirements until approved.
A14: Governing rules
A15: SITE_ARCHITECTURE_IS_PAGE_LEVEL_SOURCE_OF_TRUTH
A16: BUYER_INTENT → PAGE_JOB → CONTENT_DEPTH → PROOF_NEED → CTA
A17: META_AND_SCHEMA_BELONG_WITH_PAGE_ARCHITECTURE
A18: SCHEMA_TYPE_MUST_MATCH_ACTUAL_PAGE_CONTENT
A19: PROPOSED_PAGE != APPROVED_PAGE
A20: PROPOSED_URL != APPROVED_REDIRECT
A21: KEYWORD_OR_SEARCH_INTENT != PAGE_PURPOSE
A22: ARCHITECTURE_CHANGE_REQUIRES_DOWNSTREAM_IMPACT_REVIEW

Sheet Sitemap
A1: Sitemap
A2: Full page inventory. This tab is the page-level source of truth for architecture, buyer intent, URL, metadata, schema, dependencies, and measurement.
A4: Page ID | B4: Level | C4: Section | D4: Page | E4: Existing URL | F4: Nav Location | G4: Scope / Status | H4: Primary Buyer Intent | I4: Secondary Buyer Intent | J4: Page Objective | K4: Primary CTA | L4: Secondary CTA | M4: Proposed URL | N4: Meta Title | O4: Title Chars | P4: Meta Description | Q4: Desc Chars | R4: Primary Search Intent | S4: Target Topic | T4: Schema Type(s) | U4: Key Schema Properties | V4: Proof / Content Dependencies | W4: Measurement | X4: Redirect Requirement | Y4: Source Notes / Rationale | Z4: Approval Status | AA4: Review Flag
A5: NUV-P001 | B5: L1 | C5: Homepage | D5: Homepage | E5: / | F5: Architecture L1 | G5: ENHANCED | H5: Solution Aware | I5: Problem Aware / Product Aware | J5: Establish relevance, route corporate and individual buyers, communicate the three-pillar offer, surface proof, and create appropriate next actions. | K5: Request a Consultation | L5: Take the Self-Assessment / For Myself | M5: / | N5: Sales Training That Guarantees Results | NuVue | O5: =IF(N5="","",LEN(N5)) | P5: NuVue builds high-performing sales teams with the Counselor Salesperson method and a pay-for-performance guarantee. 24+ years of measurable revenue gains. | Q5: =IF(P5="","",LEN(P5)) | S5: Sales Training That Guarantees Results | T5: Organization, WebSite | U5: Organization: name, url, logo, description, sameAs, foundingDate (2002), contactPoint. WebSite: url, potentialAction (SearchAction). | V5: See source notes / approved proof library where applicable | W5: Buyer-path clicks; consultation starts/completions; assessment starts/completions; seminar-path clicks | X5: NO | Y5: Hero with universal pain point, dual buyer path buttons, trust bar, self-assessment quiz CTA | Sitewide Organization + WebSite belong here in the <head>. Anchors brand entity for AI search. | Z5: DRAFT — HUMAN REVIEW
A6: NUV-P002 | B6: L1 | C6: Homepage | D6: For Organizations | F6: Architecture L1 | G6: NEW | H6: Product Aware | I6: Solution Aware | J6: Help enterprise buyers evaluate NuVue as a development partner and progress toward a qualified consultation. | K6: Request a Consultation | L6: Explore Solutions | M6: /solutions-for-organizations/ | N6: Sales Training for Teams & Organizations | NuVue | O6: =IF(N6="","",LEN(N6)) | P6: Equip your sales force with proven training built for 50+ rep teams. Multi-year curricula, measurable ROI, and a results guarantee. Request a consultation. | Q6: =IF(P6="","",LEN(P6)) | S6: Sales Training for Teams & Organizations | T6: Service, BreadcrumbList | U6: Service: serviceType, provider (Organization), areaServed, audience (BusinessAudience: numberOfEmployees 50+), offers. Add BreadcrumbList. | V6: See source notes / approved proof library where applicable | W6: Consultation starts/completions; solution clicks; proof engagement | X6: NO — new URL | Y6: Corporate buyer landing — VP Sales, L&D Directors → Request a Consultation | Primary corporate buyer path. CTA: Request a Consultation. | Z6: DRAFT — HUMAN REVIEW
A7: NUV-P003 | B7: L1 | C7: Homepage | D7: For Sales Professionals | F7: Architecture L1 | G7: NEW | H7: Product Aware / Most Aware | I7: Solution Aware | J7: Help individual professionals identify the right training path and progress toward seminar or program action. | K7: Explore / Register for Public Seminars | L7: Take the Self-Assessment | M7: /solutions-for-professionals/ | N7: Sales Training for Professionals | NuVue | O7: =IF(N7="","",LEN(N7)) | P7: Sharpen your selling skills with public seminars, self-paced courses, and continuous learning. Practical sales training for new and experienced reps. | Q7: =IF(P7="","",LEN(P7)) | S7: Sales Training for Professionals | T7: Service, BreadcrumbList | U7: Service: serviceType, provider, audience (Audience: sales professionals), offers (public seminars). Add BreadcrumbList. | V7: See source notes / approved proof library where applicable | W7: Seminar-path clicks; registration starts/completions; assessment activity | X7: NO — new URL | Y7: Individual buyer landing — seminars, self-paced, assessment, LTNS membership | Individual buyer path. Growth channel for self-directed buyers. | Z7: DRAFT — HUMAN REVIEW
A8: NUV-P004 | B8: L1 | C8: Offerings | D8: Curriculum Overview | E8: /solutions/ | F8: Architecture L1 | G8: RESTRUCTURED | H8: Solution Aware | I8: Product Aware | J8: 3-pillar landing page replacing deep nested menus | K8: Explore Relevant Solution | L8: Request a Consultation | M8: /curriculum/ | N8: Sales & Leadership Training Curriculum | NuVue | O8: =IF(N8="","",LEN(N8)) | P8: Explore NuVue's full curriculum across sales, leadership, and business acumen. Filter 100+ workshops by topic, format, and level to build your program. | Q8: =IF(P8="","",LEN(P8)) | S8: Sales & Leadership Training Curriculum | T8: CollectionPage, BreadcrumbList | U8: CollectionPage: name, description, isPartOf. Add ItemList of the three pillar pages (Sales, Leadership, Business Acumen). BreadcrumbList. | V8: See source notes / approved proof library where applicable | X8: YES — 301 | Y8: 3-pillar landing page replacing deep nested menus | Three-pillar hub replacing nested menus. | Z8: DRAFT — HUMAN REVIEW
A9: NUV-P005 | B9: L2 | C9: Offerings | D9: Sales (Pillar) | E9: /solutions/sales-enablement/ | F9: Architecture L2 | G9: RESTRUCTURED | H9: Solution Aware | I9: Product Aware | J9: Pillar landing page - Sales Curriculum | K9: Explore Relevant Solution | L9: Request a Consultation | M9: /curriculum/sales/ | N9: Sales Development Training Programs | NuVue | O9: =IF(N9="","",LEN(N9)) | P9: Consultative selling, prospecting, negotiation, and more. NuVue's sales development workshops turn reps into trusted advisors who grow revenue. | Q9: =IF(P9="","",LEN(P9)) | S9: Sales Development Training Programs | T9: CollectionPage, BreadcrumbList | U9: CollectionPage with ItemList of Course items (each program). hasPart linking to course pages. BreadcrumbList. | V9: See source notes / approved proof library where applicable | X9: YES — 301 | Y9: Pillar landing page - Sales Curriculum | Pillar landing. Flagship is Counselor Salesperson. | Z9: DRAFT — HUMAN REVIEW
A10: NUV-P006 | B10: L3 | C10: Offerings | D10: Counselor Salesperson (CSP) | E10: /solutions/sales-enablement/counselor-salesperson/ | F10: Architecture L3 | G10: ENHANCED | H10: Product Aware | I10: Solution Aware | J10: Core methodology page — consultative selling approach, enhanced messaging | M10: /curriculum/sales/counselor-salesperson/ | N10: Counselor Salesperson (CSP) Training | NuVue | O10: =IF(N10="","",LEN(N10)) | P10: The flagship consultative selling method behind $400K average revenue gains per rep. Learn the Counselor Salesperson approach trusted for decades. | Q10: =IF(P10="","",LEN(P10)) | S10: Counselor Salesperson (CSP) Training | T10: Course, BreadcrumbList | U10: Course: name, description, provider, educationalLevel, hasCourseInstance (courseMode: onsite, online, blended; courseWorkload). Optional offers. BreadcrumbList. | V10: See source notes / approved proof library where applicable | X10: YES — 301 | Y10: Core methodology page — consultative selling approach, enhanced messaging | Flagship program. Tie to CSP Guarantee + Ag Edition. | Z10: DRAFT — HUMAN REVIEW
A11: NUV-P007 | B11: L3 | C11: Offerings | D11: Counselor Prospecting | E11: /solutions/sales-enablement/counselor-prospecting/ | F11: Architecture L3 | G11: EXISTS | H11: Product Aware | I11: Solution Aware | J11: Existing program, new URL path | M11: /curriculum/sales/counselor-prospecting/ | O11: =IF(N11="","",LEN(N11)) | Q11: =IF(P11="","",LEN(P11)) | V11: See source notes / approved proof library where applicable | X11: YES — 301 | Y11: Existing program, new URL path | Z11: DRAFT — HUMAN REVIEW | AA11: Metadata, Schema
A12: NUV-P008 | B12: L3 | C12: Offerings | D12: Selling in a Virtual Environment | E12: /solutions/sales-enablement/selling-in-a-virtual-environment/ | F12: Architecture L3 | G12: EXISTS | H12: Product Aware | I12: Solution Aware | M12: /curriculum/sales/selling-in-a-virtual-environment/ | O12: =IF(N12="","",LEN(N12)) | Q12: =IF(P12="","",LEN(P12)) | V12: See source notes / approved proof library where applicable | X12: YES — 301 | Z12: DRAFT — HUMAN REVIEW | AA12: Page objective, Metadata, Schema
A13: NUV-P009 | B13: L3 | C13: Offerings | D13: Mastering Successful Presentations | E13: /solutions/sales-enablement/mastering-successful-presentations-skills-for-influencing-outcomes/ | F13: Architecture L3 | G13: EXISTS | H13: Product Aware | I13: Solution Aware | J13: Existing program, shortened URL | M13: /curriculum/sales/presentations/ | O13: =IF(N13="","",LEN(N13)) | Q13: =IF(P13="","",LEN(P13)) | V13: See source notes / approved proof library where applicable | X13: YES — 301 | Y13: Existing program, shortened URL | Z13: DRAFT — HUMAN REVIEW | AA13: Metadata, Schema
A14: NUV-P010 | B14: L3 | C14: Offerings | D14: Versatile Salesperson | E14: /solutions/sales-enablement/versatile-salesperson/ | F14: Architecture L3 | G14: EXISTS | H14: Product Aware | I14: Solution Aware | J14: Existing program, new URL path | M14: /curriculum/sales/versatile-salesperson/ | O14: =IF(N14="","",LEN(N14)) | Q14: =IF(P14="","",LEN(P14)) | V14: See source notes / approved proof library where applicable | X14: YES — 301 | Y14: Existing program, new URL path | Z14: DRAFT — HUMAN REVIEW | AA14: Metadata, Schema
A15: NUV-P011 | B15: L3 | C15: Offerings | D15: Selling to the Generations | E15: /solutions/sales-enablement/selling-to-the-generations/ | F15: Architecture L3 | G15: EXISTS | H15: Product Aware | I15: Solution Aware | J15: Existing program, new URL path | M15: /curriculum/sales/selling-to-the-generations/ | O15: =IF(N15="","",LEN(N15)) | Q15: =IF(P15="","",LEN(P15)) | V15: See source notes / approved proof library where applicable | X15: YES — 301 | Y15: Existing program, new URL path | Z15: DRAFT — HUMAN REVIEW | AA15: Metadata, Schema
A16: NUV-P012 | B16: L3 | C16: Offerings | D16: Turning Information into Sales | E16: /solutions/sales-enablement/turning-information-into-sales/ | F16: Architecture L3 | G16: EXISTS | H16: Product Aware | I16: Solution Aware | J16: Existing program, new URL path | M16: /curriculum/sales/turning-information-into-sales/ | O16: =IF(N16="","",LEN(N16)) | Q16: =IF(P16="","",LEN(P16)) | V16: See source notes / approved proof library where applicable | X16: YES — 301 | Y16: Existing program, new URL path | Z16: DRAFT — HUMAN REVIEW | AA16: Metadata, Schema
A17: NUV-P013 | B17: L3 | C17: Offerings | D17: Negotiating to Yes | E17: /solutions/sales-enablement/negotiating-to-yes-sales-edition/ | F17: Architecture L3 | G17: EXISTS | H17: Product Aware | I17: Solution Aware | J17: Existing program, new URL path | M17: /curriculum/sales/negotiating-to-yes/ | O17: =IF(N17="","",LEN(N17)) | Q17: =IF(P17="","",LEN(P17)) | V17: See source notes / approved proof library where applicable | X17: YES — 301 | Y17: Existing program, new URL path | Z17: DRAFT — HUMAN REVIEW | AA17: Metadata, Schema
A18: NUV-P014 | B18: L3 | C18: Offerings | D18: Time Management for Salespeople | E18: /solutions/sales-enablement/time-management-for-salespeople/ | F18: Architecture L3 | G18: EXISTS | H18: Product Aware | I18: Solution Aware | J18: Existing program, new URL path | M18: /curriculum/sales/time-management/ | O18: =IF(N18="","",LEN(N18)) | Q18: =IF(P18="","",LEN(P18)) | V18: See source notes / approved proof library where applicable | X18: YES — 301 | Y18: Existing program, new URL path | Z18: DRAFT — HUMAN REVIEW | AA18: Metadata, Schema
A19: NUV-P015 | B19: L3 | C19: Offerings | D19: Coaching the Counselor Salesperson | E19: /solutions/sales-enablement/coaching-the-counselor-salesperson/ | F19: Architecture L3 | G19: EXISTS | H19: Product Aware | I19: Solution Aware | J19: Existing program, new URL path | M19: /curriculum/sales/coaching-the-counselor-salesperson/ | O19: =IF(N19="","",LEN(N19)) | Q19: =IF(P19="","",LEN(P19)) | V19: See source notes / approved proof library where applicable | X19: YES — 301 | Y19: Existing program, new URL path | Z19: DRAFT — HUMAN REVIEW | AA19: Metadata, Schema
A20: NUV-P016 | B20: L3 | C20: Offerings | D20: Sales Advantage Series | E20: /solutions/sales-enablement/sales-advantage-series/ | F20: Architecture L3 | G20: EXISTS | H20: Product Aware | I20: Solution Aware | J20: Existing program, new URL path | M20: /curriculum/sales/sales-advantage-series/ | O20: =IF(N20="","",LEN(N20)) | Q20: =IF(P20="","",LEN(P20)) | V20: See source notes / approved proof library where applicable | X20: YES — 301 | Y20: Existing program, new URL path | Z20: DRAFT — HUMAN REVIEW | AA20: Metadata, Schema
A21: NUV-P017 | B21: L3 | C21: Offerings | D21: Trade Show Selling | E21: /solutions/sales-enablement/trade-show-selling/ | F21: Architecture L3 | G21: EXISTS | H21: Product Aware | I21: Solution Aware | J21: Existing program, new URL path | M21: /curriculum/sales/trade-show-selling/ | O21: =IF(N21="","",LEN(N21)) | Q21: =IF(P21="","",LEN(P21)) | V21: See source notes / approved proof library where applicable | X21: YES — 301 | Y21: Existing program, new URL path | Z21: DRAFT — HUMAN REVIEW | AA21: Metadata, Schema
A22: NUV-P018 | B22: L3 | C22: Offerings | D22: Value-Added Selling | E22: /solutions/sales-enablement/value-added-selling/ | F22: Architecture L3 | G22: EXISTS | H22: Product Aware | I22: Solution Aware | J22: Existing program, new URL path | M22: /curriculum/sales/value-added-selling/ | O22: =IF(N22="","",LEN(N22)) | Q22: =IF(P22="","",LEN(P22)) | V22: See source notes / approved proof library where applicable | X22: YES — 301 | Y22: Existing program, new URL path | Z22: DRAFT — HUMAN REVIEW | AA22: Metadata, Schema
A23: NUV-P019 | B23: L3 | C23: Offerings | D23: Sales Assessments | E23: /solutions/assessments/sales-assessments/ | F23: Architecture L3 | G23: MOVED | H23: Product Aware | I23: Solution Aware | J23: Existing | M23: /curriculum/sales/sales-assessments/ | O23: =IF(N23="","",LEN(N23)) | Q23: =IF(P23="","",LEN(P23)) | V23: See source notes / approved proof library where applicable | X23: YES — 301 | Y23: Existing | Z23: DRAFT — HUMAN REVIEW | AA23: Metadata, Schema
A24: NUV-P020 | B24: L2 | C24: Offerings | D24: Leadership (Pillar) | E24: /solutions/leadership/ | F24: Architecture L2 | G24: RESTRUCTURED | H24: Solution Aware | I24: Product Aware | J24: Pillar landing — 18+ workshops + executive coaching combined | K24: Explore Relevant Solution | L24: Request a Consultation | M24: /curriculum/leadership/ | N24: Leadership & Executive Coaching Programs | NuVue | O24: =IF(N24="","",LEN(N24)) | P24: Develop managers and executives with 18+ leadership workshops and one-on-one coaching. Build engaged teams and leaders who drive performance. | Q24: =IF(P24="","",LEN(P24)) | S24: Leadership & Executive Coaching Programs | T24: CollectionPage, BreadcrumbList | U24: CollectionPage with ItemList of Course/Service items. hasPart linking to program pages. BreadcrumbList. | V24: See source notes / approved proof library where applicable | X24: YES — 301 | Y24: Pillar landing — 18+ workshops + executive coaching combined | Pillar landing; absorbs team-building + coaching programs. | Z24: DRAFT — HUMAN REVIEW
A25: NUV-P021 | B25: L3 | C25: Offerings | D25: Executive Coaching | E25: /solutions/coaching/executive-coaching/ | F25: Architecture L3 | G25: ENHANCED | H25: Product Aware | I25: Solution Aware | J25: Dedicated page — new managers to C-suite. Moved from /coaching/ | M25: /curriculum/leadership/executive-coaching/ | N25: Executive Coaching Services | NuVue | O25: =IF(N25="","",LEN(N25)) | P25: One-on-one executive coaching for new managers to the C-suite. Personalized development that strengthens leadership, decisions, and team results. | Q25: =IF(P25="","",LEN(P25)) | S25: Executive Coaching Services | T25: Service, BreadcrumbList | U25: Service: serviceType (Executive Coaching), provider, audience, areaServed. BreadcrumbList. (Use Service, not Course - it is 1:1, not scheduled.) | V25: See source notes / approved proof library where applicable | X25: YES — 301 | Y25: Dedicated page — new managers to C-suite. Moved from /coaching/ | Moved from /coaching/ into Leadership pillar. | Z25: DRAFT — HUMAN REVIEW
A26: NUV-P022 | B26: L3 | C26: Offerings | D26: Building Relationship Versatility | E26: /solutions/leadership/building-relationship-versatility/ | F26: Architecture L3 | G26: EXISTS | H26: Product Aware | I26: Solution Aware | J26: Existing program | M26: /curriculum/leadership/building-relationship-versatility/ | O26: =IF(N26="","",LEN(N26)) | Q26: =IF(P26="","",LEN(P26)) | V26: See source notes / approved proof library where applicable | X26: YES — 301 | Y26: Existing program | Z26: DRAFT — HUMAN REVIEW | AA26: Metadata, Schema
A27: NUV-P023 | B27: L3 | C27: Offerings | D27: Coaching for Performance | E27: /solutions/leadership/coaching-for-performance/ | F27: Architecture L3 | G27: EXISTS | H27: Product Aware | I27: Solution Aware | J27: Existing program | M27: /curriculum/leadership/coaching-for-performance/ | O27: =IF(N27="","",LEN(N27)) | Q27: =IF(P27="","",LEN(P27)) | V27: See source notes / approved proof library where applicable | X27: YES — 301 | Y27: Existing program | Z27: DRAFT — HUMAN REVIEW | AA27: Metadata, Schema
A28: NUV-P024 | B28: L3 | C28: Offerings | D28: Coaching for Sales Performance | E28: /solutions/leadership/coaching-for-sales-performance/ | F28: Architecture L3 | G28: EXISTS | H28: Product Aware | I28: Solution Aware | J28: Existing program | M28: /curriculum/leadership/coaching-for-sales-performance/ | O28: =IF(N28="","",LEN(N28)) | Q28: =IF(P28="","",LEN(P28)) | V28: See source notes / approved proof library where applicable | X28: YES — 301 | Y28: Existing program | Z28: DRAFT — HUMAN REVIEW | AA28: Metadata, Schema
A29: NUV-P025 | B29: L3 | C29: Offerings | D29: Communicating with Purpose | E29: /solutions/leadership/communicating-with-purpose/ | F29: Architecture L3 | G29: EXISTS | H29: Product Aware | I29: Solution Aware | J29: Existing program | M29: /curriculum/leadership/communicating-with-purpose/ | O29: =IF(N29="","",LEN(N29)) | Q29: =IF(P29="","",LEN(P29)) | V29: See source notes / approved proof library where applicable | X29: YES — 301 | Y29: Existing program | Z29: DRAFT — HUMAN REVIEW | AA29: Metadata, Schema
A30: NUV-P026 | B30: L3 | C30: Offerings | D30: Managing Conflict | E30: /solutions/leadership/managing-conflict/ | F30: Architecture L3 | G30: EXISTS | H30: Product Aware | I30: Solution Aware | J30: Existing program | M30: /curriculum/leadership/managing-conflict/ | O30: =IF(N30="","",LEN(N30)) | Q30: =IF(P30="","",LEN(P30)) | V30: See source notes / approved proof library where applicable | X30: YES — 301 | Y30: Existing program | Z30: DRAFT — HUMAN REVIEW | AA30: Metadata, Schema
A31: NUV-P027 | B31: L3 | C31: Offerings | D31: Managing Styles in Conflict | E31: /solutions/leadership/managing-styles-in-conflict/ | F31: Architecture L3 | G31: EXISTS | H31: Product Aware | I31: Solution Aware | J31: Existing program | M31: /curriculum/leadership/managing-styles-in-conflict/ | O31: =IF(N31="","",LEN(N31)) | Q31: =IF(P31="","",LEN(P31)) | V31: See source notes / approved proof library where applicable | X31: YES — 301 | Y31: Existing program | Z31: DRAFT — HUMAN REVIEW | AA31: Metadata, Schema
A32: NUV-P028 | B32: L3 | C32: Offerings | D32: Meeting Leadership Challenges | E32: /solutions/leadership/meeting-leadership-challenges/ | F32: Architecture L3 | G32: EXISTS | H32: Product Aware | I32: Solution Aware | J32: Existing program | M32: /curriculum/leadership/meeting-leadership-challenges/ | O32: =IF(N32="","",LEN(N32)) | Q32: =IF(P32="","",LEN(P32)) | V32: See source notes / approved proof library where applicable | X32: YES — 301 | Y32: Existing program | Z32: DRAFT — HUMAN REVIEW | AA32: Metadata, Schema
A33: NUV-P029 | B33: L3 | C33: Offerings | D33: Delegating with Confidence | E33: /solutions/leadership/delegating-with-confidence/ | F33: Architecture L3 | G33: EXISTS | H33: Product Aware | I33: Solution Aware | J33: Existing program | M33: /curriculum/leadership/delegating-with-confidence/ | O33: =IF(N33="","",LEN(N33)) | Q33: =IF(P33="","",LEN(P33)) | V33: See source notes / approved proof library where applicable | X33: YES — 301 | Y33: Existing program | Z33: DRAFT — HUMAN REVIEW | AA33: Metadata, Schema
A34: NUV-P030 | B34: L3 | C34: Offerings | D34: Leading from Within | E34: /solutions/leadership/leading-from-within/ | F34: Architecture L3 | G34: EXISTS | H34: Product Aware | I34: Solution Aware | J34: Existing program | M34: /curriculum/leadership/leading-from-within/ | O34: =IF(N34="","",LEN(N34)) | Q34: =IF(P34="","",LEN(P34)) | V34: See source notes / approved proof library where applicable | X34: YES — 301 | Y34: Existing program | Z34: DRAFT — HUMAN REVIEW | AA34: Metadata, Schema
A35: NUV-P031 | B35: L3 | C35: Offerings | D35: Leading in Challenging Times | E35: /solutions/leadership/leading-in-challenging-times/ | F35: Architecture L3 | G35: EXISTS | H35: Product Aware | I35: Solution Aware | J35: Existing program | M35: /curriculum/leadership/leading-in-challenging-times/ | O35: =IF(N35="","",LEN(N35)) | Q35: =IF(P35="","",LEN(P35)) | V35: See source notes / approved proof library where applicable | X35: YES — 301 | Y35: Existing program | Z35: DRAFT — HUMAN REVIEW | AA35: Metadata, Schema
A36: NUV-P032 | B36: L3 | C36: Offerings | D36: The Leader-Manager | E36: /solutions/leadership/the-leader-manager/ | F36: Architecture L3 | G36: EXISTS | H36: Product Aware | I36: Solution Aware | J36: Existing program | M36: /curriculum/leadership/the-leader-manager/ | O36: =IF(N36="","",LEN(N36)) | Q36: =IF(P36="","",LEN(P36)) | V36: See source notes / approved proof library where applicable | X36: YES — 301 | Y36: Existing program | Z36: DRAFT — HUMAN REVIEW | AA36: Metadata, Schema
A37: NUV-P033 | B37: L3 | C37: Offerings | D37: Creating a Culture of Engagement | E37: /solutions/leadership/creating-a-culture-of-engagement/ | F37: Architecture L3 | G37: EXISTS | H37: Product Aware | I37: Solution Aware | J37: Existing program | M37: /curriculum/leadership/creating-a-culture-of-engagement/ | O37: =IF(N37="","",LEN(N37)) | Q37: =IF(P37="","",LEN(P37)) | V37: See source notes / approved proof library where applicable | X37: YES — 301 | Y37: Existing program | Z37: DRAFT — HUMAN REVIEW | AA37: Metadata, Schema
... A39: NUV-P035 | B39: L3 | C39: Offerings | D39: Global Effectiveness | E39: /solutions/leadership/global-effectiveness/ | F39: Architecture L3 | G39: EXISTS | H39: Product Aware | I39: Solution Aware | J39: Existing program | M39: /curriculum/leadership/global-effectiveness/ | O39: =IF(N39="","",LEN(N39)) | Q39: =IF(P39="","",LEN(P39)) | V39: See source notes / approved proof library where applicable | X39: YES — 301 | Y39: Existing program | Z39: DRAFT — HUMAN REVIEW | AA39: Metadata, Schema
A40: NUV-P036 | B40: L3 | C40: Offerings | D40: Motivating for Results | E40: /solutions/leadership/motivating-for-results/ | F40: Architecture L3 | G40: EXISTS | H40: Product Aware | J40: Existing program | M40: /curriculum/leadership/motivating-for-results/ | O40: =IF(N40="","",LEN(N40)) | Q40: =IF(P40="","",LEN(P40)) | V40: See source notes / approved proof library where applicable | X40: YES — 301 | Y40: Existing program | Z40: DRAFT — HUMAN REVIEW | AA40: Metadata, Schema
A41: NUV-P037 | B41: L3 | C41: Offerings | D41: Leading for Growth | E41: /solutions/leadership/leading-for-growth/ | F41: Architecture L3 | G41: EXISTS | H41: Product Aware | I41: Solution Aware | J41: Existing program | M41: /curriculum/leadership/leading-for-growth/ | O41: =IF(N41="","",LEN(N41)) | Q41: =IF(P41="","",LEN(P41)) | V41: See source notes / approved proof library where applicable | X41: YES — 301 | Y41: Existing program | Z41: DRAFT — HUMAN REVIEW | AA41: Metadata, Schema
A42: NUV-P038 | B42: L3 | C42: Offerings | D42: Interviewing for Selection | E42: /solutions/leadership/interviewing-for-selection/ | F42: Architecture L3 | G42: EXISTS | H42: Product Aware | I42: Solution Aware | J42: Existing program | M42: /curriculum/leadership/interviewing-for-selection/ | O42: =IF(N42="","",LEN(N42)) | Q42: =IF(P42="","",LEN(P42)) | V42: See source notes / approved proof library where applicable | X42: YES — 301 | Y42: Existing program | Z42: DRAFT — HUMAN REVIEW | AA42: Metadata, Schema
A43: NUV-P039 | B43: L3 | C43: Offerings | D43: Consulting with Clients | E43: /solutions/leadership/consulting-with-clients/ | F43: Architecture L3 | G43: EXISTS | H43: Product Aware | I43: Solution Aware | J43: Existing program | M43: /curriculum/leadership/consulting-with-clients/ | O43: =IF(N43="","",LEN(N43)) | Q43: =IF(P43="","",LEN(P43)) | V43: See source notes / approved proof library where applicable | X43: YES — 301 | Y43: Existing program | Z43: DRAFT — HUMAN REVIEW | AA43: Metadata, Schema
A44: NUV-P040 | B44: L3 | C44: Offerings | D44: Work-Life Balance | E44: /solutions/leadership/work-life-balance/ | F44: Architecture L3 | G44: EXISTS | H44: Product Aware | I44: Solution Aware | J44: Existing program | M44: /curriculum/leadership/work-life-balance/ | O44: =IF(N44="","",LEN(N44)) | Q44: =IF(P44="","",LEN(P44)) | V44: See source notes / approved proof library where applicable | X44: YES — 301 | Y44: Existing program | Z44: DRAFT — HUMAN REVIEW | AA44: Metadata, Schema
A45: NUV-P041 | B45: L3 | C45: Offerings | D45: Working Styles / Social Styles | E45: /solutions/leadership/working-styles-dimensions-of-social-styles/ | F45: Architecture L3 | G45: EXISTS | H45: Product Aware | I45: Solution Aware | J45: Existing program, shortened URL | M45: /curriculum/leadership/working-styles/ | O45: =IF(N45="","",LEN(N45)) | Q45: =IF(P45="","",LEN(P45)) | V45: See source notes / approved proof library where applicable | X45: YES — 301 | Y45: Existing program, shortened URL | Z45: DRAFT — HUMAN REVIEW | AA45: Metadata, Schema
A46: NUV-P042 | B46: L3 | C46: Offerings | D46: Building High-Performance Teams | E46: /solutions/team-building/building-high-performance-teams/ | F46: Architecture L3 | G46: MOVED | H46: Product Aware | I46: Solution Aware | J46: Moved from Team Building to Leadership pillar | M46: /curriculum/leadership/building-high-performance-teams/ | O46: =IF(N46="","",LEN(N46)) | Q46: =IF(P46="","",LEN(P46)) | V46: See source notes / approved proof library where applicable | X46: YES — 301 | Y46: Moved from Team Building to Leadership pillar | Z46: DRAFT — HUMAN REVIEW | AA46: Metadata, Schema
A47: NUV-P043 | B47: L3 | C47: Offerings | D47: Virtual Coaching | E47: /solutions/coaching/virtual-coaching/ | F47: Architecture L3 | G47: EXISTS | H47: Product Aware | I47: Solution Aware | J47: Moved from /coaching/ to Leadership pillar | M47: /curriculum/leadership/virtual-coaching/ | O47: =IF(N47="","",LEN(N47)) | Q47: =IF(P47="","",LEN(P47)) | V47: See source notes / approved proof library where applicable | X47: YES — 301 | Y47: Moved from /coaching/ to Leadership pillar | Z47: DRAFT — HUMAN REVIEW | AA47: Metadata, Schema
A48: NUV-P044 | B48: L3 | C48: Offerings | D48: Leadership Assessments | E48: /solutions/assessments/leadership-assessments/ | F48: Architecture L3 | G48: MOVED | H48: Product Aware | I48: Solution Aware | J48: Existing | M48: /curriculum/leadership/leadership-assessments/ | O48: =IF(N48="","",LEN(N48)) | Q48: =IF(P48="","",LEN(P48)) | V48: See source notes / approved proof library where applicable | X48: YES — 301 | Y48: Existing | Z48: DRAFT — HUMAN REVIEW | AA48: Metadata, Schema
A49: NUV-P045 | B49: L3 | C49: Offerings | D49: ARA Navigator 360 | E49: /solutions/assessments/the-ara-navigator-360/ | F49: Architecture L3 | G49: EXISTS | H49: Product Aware | I49: Solution Aware | J49: Existing, shortened URL | M49: /curriculum/leadership/ara-navigator-360/ | O49: =IF(N49="","",LEN(N49)) | Q49: =IF(P49="","",LEN(P49)) | V49: See source notes / approved proof library where applicable | X49: YES — 301 | Y49: Existing, shortened URL | Z49: DRAFT — HUMAN REVIEW | AA49: Metadata, Schema
A50: NUV-P046 | B50: L2 | C50: Offerings | D50: Business Acumen (Pillar) | E50: /solutions/business-acumen/ | F50: Architecture L2 | G50: RESTRUCTURED | H50: Solution Aware | I50: Product Aware | J50: Pillar landing — Income|Outcome + financial literacy programs | K50: Explore Relevant Solution | L50: Request a Consultation | M50: /curriculum/business-acumen/ | N50: Business Acumen & Financial Literacy Training | NuVue | O50: =IF(N50="","",LEN(N50)) | P50: Help teams understand how the business makes money. Income|Outcome simulations and finance workshops that connect daily decisions to the bottom line. | Q50: =IF(P50="","",LEN(P50)) | S50: Business Acumen & Financial Literacy Training | T50: CollectionPage, BreadcrumbList | U50: CollectionPage with ItemList of Course items. hasPart linking to program pages. BreadcrumbList. | V50: See source notes / approved proof library where applicable | X50: YES — 301 | Y50: Pillar landing — Income|Outcome + financial literacy programs | Pillar landing; featured program is Income|Outcome. | Z50: DRAFT — HUMAN REVIEW
A51: NUV-P047 | B51: L3 | C51: Offerings | D51: Income|Outcome Business Simulation | E51: /solutions/business-acumen/business-basics/ | F51: Architecture L3 | G51: ENHANCED | H51: Product Aware | I51: Solution Aware | J51: Featured program — financial literacy simulation, enhanced positioning | M51: /curriculum/business-acumen/income-outcome/ | N51: Income|Outcome Business Simulation | NuVue | O51: =IF(N51="","",LEN(N51)) | P51: A hands-on board simulation that teaches financial literacy by running a business. Teams learn how their decisions drive cash, profit, and growth. | Q51: =IF(P51="","",LEN(P51)) | S51: Income|Outcome Business Simulation | T51: Course, BreadcrumbList | U51: Course: name, description, provider, hasCourseInstance (courseMode: onsite/blended). BreadcrumbList. | V51: See source notes / approved proof library where applicable | X51: YES — 301 | Y51: Featured program — financial literacy simulation, enhanced positioning | Featured business-acumen program. | Z51: DRAFT — HUMAN REVIEW
A52: NUV-P048 | B52: L3 | C52: Offerings | D52: Finance for Sales Professionals | E52: /solutions/business-acumen/finance-for-sales-professionals/ | F52: Architecture L3 | G52: EXISTS | H52: Product Aware / Most Aware | I52: Solution Aware | J52: Existing program | M52: /curriculum/business-acumen/finance-for-sales-professionals/ | O52: =IF(N52="","",LEN(N52)) | Q52: =IF(P52="","",LEN(P52)) | V52: See source notes / approved proof library where applicable | X52: YES — 301 | Y52: Existing program | Z52: DRAFT — HUMAN REVIEW | AA52: Metadata, Schema
A53: NUV-P049 | B53: L3 | C53: Offerings | D53: Finance for Managers & Executives | E53: /solutions/business-acumen/finance-for-managers-and-executives/ | F53: Architecture L3 | G53: EXISTS | H53: Product Aware | I53: Solution Aware | J53: Existing program | M53: /curriculum/business-acumen/finance-for-managers-and-executives/ | O53: =IF(N53="","",LEN(N53)) | Q53: =IF(P53="","",LEN(P53)) | V53: See source notes / approved proof library where applicable | X53: YES — 301 | Y53: Existing program | Z53: DRAFT — HUMAN REVIEW | AA53: Metadata, Schema
A54: NUV-P050 | B54: L3 | C54: Offerings | D54: Finance for Everyone | E54: /solutions/business-acumen/finance-for-everyone/ | F54: Architecture L3 | G54: EXISTS | H54: Product Aware | I54: Solution Aware | J54: Existing program | M54: /curriculum/business-acumen/finance-for-everyone/ | O54: =IF(N54="","",LEN(N54)) | Q54: =IF(P54="","",LEN(P54)) | V54: See source notes / approved proof library where applicable | X54: YES — 301 | Y54: Existing program | Z54: DRAFT — HUMAN REVIEW | AA54: Metadata, Schema
A55: NUV-P051 | B55: L1 | C55: Offerings | D55: Team Building | E55: /solutions/team-building/ | F55: Architecture L1 | G55: EXISTS | H55: TBD — HUMAN REVIEW | J55: Programs absorbed into Leadership pillar | O55: =IF(N55="","",LEN(N55)) | Q55: =IF(P55="","",LEN(P55)) | V55: See source notes / approved proof library where applicable | Y55: Programs absorbed into Leadership pillar | Z55: DRAFT — HUMAN REVIEW | AA55: Buyer intent, Metadata, Schema
A56: NUV-P052 | B56: L1 | C56: Offerings | D56: Industries We Serve | E56: /industries-we-serve/ | F56: Architecture L1 | G56: ENHANCED | H56: Solution Aware | I56: Product Aware | J56: Problem-first landing pages for each vertical | M56: /industries/ | N56: Industries We Serve | Sales Training | NuVue | O56: =IF(N56="","",LEN(N56)) | P56: Industry-specific sales and leadership training for agriculture, manufacturing, insurance, healthcare, and more. Programs tailored to your market. | Q56: =IF(P56="","",LEN(P56)) | S56: Industries We Serve | Sales Training | T56: CollectionPage, BreadcrumbList | U56: CollectionPage with ItemList of the six industry pages. BreadcrumbList. | V56: See source notes / approved proof library where applicable | X56: YES — 301 | Y56: Problem-first landing pages for each vertical | Problem-first vertical hub. | Z56: DRAFT — HUMAN REVIEW
A57: NUV-P053 | B57: L2 | C57: Offerings | D57: Agriculture | E57: /industries-we-serve/agriculture/ | F57: Architecture L2 | G57: ENHANCED | H57: TBD — HUMAN REVIEW | J57: CSP Ag Edition featured, BASF expertise, ag-specific case studies | M57: /industries/agriculture/ | N57: Agriculture Sales Training | NuVue | O57: =IF(N57="","",LEN(N57)) | P57: Sales training built for agriculture, from agronomy sales onboarding to the Counselor Salesperson Ag Edition. Backed by deep ag-industry experience. | Q57: =IF(P57="","",LEN(P57)) | S57: Agriculture Sales Training | T57: Service, BreadcrumbList | U57: Service: serviceType, provider, areaServed, audience (agriculture/agronomy sales). BreadcrumbList. Optional Offer for Ag Onboarding ($12,000/yr). | V57: See source notes / approved proof library where applicable | X57: YES — 301 | Y57: CSP Ag Edition featured, BASF expertise, ag-specific case studies | Strongest vertical. BASF/ag heritage; CSP Ag Edition featured. | Z57: DRAFT — HUMAN REVIEW | AA57: Buyer intent
A58: NUV-P054 | B58: L2 | C58: Offerings | D58: Manufacturing | E58: /industries-we-serve/manufacturing/ | F58: Architecture L2 | G58: ENHANCED | H58: TBD — HUMAN REVIEW | J58: Industry-specific messaging and case studies | M58: /industries/manufacturing/ | N58: Manufacturing Sales Training | NuVue | O58: =IF(N58="","",LEN(N58)) | P58: Sales and leadership training for manufacturers. Help technical sales teams sell value, manage complex deals, and build stronger customer relationships. | Q58: =IF(P58="","",LEN(P58)) | S58: Manufacturing Sales Training | T58: Service, BreadcrumbList | U58: Service: serviceType, provider, areaServed (Manufacturing), audience. BreadcrumbList. | V58: See source notes / approved proof library where applicable | X58: YES — 301 | Y58: Industry-specific messaging and case studies | Industry-specific messaging + case studies. | Z58: DRAFT — HUMAN REVIEW | AA58: Buyer intent
A59: NUV-P055 | B59: L2 | C59: Offerings | D59: Insurance & Financial Services | E59: /industries-we-serve/financial-services-and-insurance/ | F59: Architecture L2 | G59: ENHANCED | H59: TBD — HUMAN REVIEW | J59: Combined vertical with tailored content | M59: /industries/insurance-financial-services/ | N59: Insurance & Financial Services Sales Training | NuVue | O59: =IF(N59="","",LEN(N59)) | P59: Consultative sales training for insurance and financial services teams. Build trust, navigate compliance, and turn advisors into trusted partners. | Q59: =IF(P59="","",LEN(P59)) | S59: Insurance & Financial Services Sales Training | T59: Service, BreadcrumbList | U59: Service: serviceType, provider, areaServed, audience. BreadcrumbList. | V59: See source notes / approved proof library where applicable | X59: YES — 301 | Y59: Combined vertical with tailored content | Combined vertical. | Z59: DRAFT — HUMAN REVIEW | AA59: Buyer intent
A60: NUV-P056 | B60: L2 | C60: Offerings | D60: Turf & Horticulture | E60: /industries-we-serve/turf-horticulture/ | F60: Architecture L2 | G60: EXISTS | H60: TBD — HUMAN REVIEW | J60: Existing vertical | M60: /industries/turf-horticulture/ | N60: Turf & Horticulture Sales Training | NuVue | O60: =IF(N60="","",LEN(N60)) | P60: Sales training tailored to turf and horticulture suppliers. Help technical reps sell value, build grower relationships, and grow account revenue. | Q60: =IF(P60="","",LEN(P60)) | S60: Turf & Horticulture Sales Training | T60: Service, BreadcrumbList | U60: Service: serviceType, provider, areaServed, audience. BreadcrumbList. | V60: See source notes / approved proof library where applicable | X60: YES — 301 | Y60: Existing vertical | Niche vertical adjacent to Agriculture. | Z60: DRAFT — HUMAN REVIEW | AA60: Buyer intent
A61: NUV-P057 | B61: L2 | C61: Offerings | D61: Sales & Services | E61: /industries-we-serve/sales-and-services/ | F61: Architecture L2 | G61: EXISTS | H61: TBD — HUMAN REVIEW | J61: Existing vertical | M61: /industries/sales-and-services/ | N61: Sales & Services Industry Training | NuVue | O61: =IF(N61="","",LEN(N61)) | P61: Consultative sales training for sales and service organizations. Turn every customer interaction into a chance to add value and grow revenue. | Q61: =IF(P61="","",LEN(P61)) | S61: Sales & Services Industry Training | T61: Service, BreadcrumbList | U61: Service: serviceType, provider, areaServed, audience. BreadcrumbList. | V61: See source notes / approved proof library where applicable | X61: YES — 301 | Y61: Existing vertical | Broad services vertical. | Z61: DRAFT — HUMAN REVIEW | AA61: Buyer intent
A62: NUV-P058 | B62: L2 | C62: Offerings | D62: Healthcare, Science & Biotech | E62: /industries-we-serve/healthcare-science-biotech/ | F62: Architecture L2 | G62: EXISTS | H62: TBD — HUMAN REVIEW | J62: Existing vertical | M62: /industries/healthcare-science-biotech/ | N62: Healthcare, Science & Biotech Sales Training | NuVue | O62: =IF(N62="","",LEN(N62)) | P62: Specialized sales training for healthcare, science, and biotech teams. Communicate complex value to technical buyers and build lasting relationships. | Q62: =IF(P62="","",LEN(P62)) | S62: Healthcare, Science & Biotech Sales Training | T62: Service, BreadcrumbList | U62: Service: serviceType, provider, areaServed, audience. BreadcrumbList. | V62: See source notes / approved proof library where applicable | X62: YES — 301 | Y62: Existing vertical | Technical-buyer vertical. | Z62: DRAFT — HUMAN REVIEW | AA62: Buyer intent
A63: NUV-P059 | B63: L1 | C63: Offerings | D63: Resources | F63: Architecture L1 | G63: RESTRUCTURED | H63: Symptom Aware | I63: Unaware / Problem Aware | J63: Content hub for SEO/AEO visibility | K63: Read / Explore | M63: /resources/ | N63: Sales Training Resources & Insights | NuVue | O63: =IF(N63="","",LEN(N63)) | P63: Articles, podcasts, case studies, and assessments to sharpen your sales and leadership skills. Free, practical insights from NuVue's training experts. | Q63: =IF(P63="","",LEN(P63)) | S63: Sales Training Resources & Insights | T63: CollectionPage, BreadcrumbList | U63: CollectionPage with ItemList of resource sub-sections. BreadcrumbList. | V63: See source notes / approved proof library where applicable | Y63: Content hub for SEO/AEO visibility | Content hub for SEO/AEO visibility. | Z63: DRAFT — HUMAN REVIEW
A64: NUV-P060 | B64: L2 | C64: Offerings | D64: Assessments | E64: /solutions/assessments/ | F64: Architecture L2 | G64: MOVED | H64: TBD — HUMAN REVIEW | J64: Assessment tools hub | M64: /resources/assessments/ | N64: Free Sales & Leadership Assessments | NuVue | O64: =IF(N64="","",LEN(N64)) | P64: Find what's holding your sales team back. Take a free NuVue assessment to benchmark skills and uncover where targeted training drives the most gains. | Q64: =IF(P64="","",LEN(P64)) | S64: Free Sales & Leadership Assessments | T64: WebPage, BreadcrumbList | U64: WebPage: name, description, primaryImageOfPage. Optional FAQPage if Q&A present. BreadcrumbList. (Lead magnet - pair with form.) | V64: See source notes / approved proof library where applicable | X64: YES — 301 | Y64: Assessment tools hub | Lead-magnet hub feeding the quiz/CTA. | Z64: DRAFT — HUMAN REVIEW | AA64: Buyer intent
A65: NUV-P061 | B65: L2 | C65: Offerings | D65: Blog | E65: /blog/ | F65: Architecture L2 | G65: ENHANCED | H65: Symptom Aware | I65: Unaware / Problem Aware | J65: Revived content engine — editorial calendar per audit | K65: Read / Explore | M65: /resources/blog/ | N65: Sales & Leadership Blog | NuVue | O65: =IF(N65="","",LEN(N65)) | P65: Practical strategies on consultative selling, sales leadership, and team performance. Insights from NuVue's coaches to help you sell and lead better. | Q65: =IF(P65="","",LEN(P65)) | S65: Sales & Leadership Blog | T65: Blog, BreadcrumbList | U65: Blog: name, description, publisher. Each post: BlogPosting (headline, author, datePublished, image). BreadcrumbList. | V65: See source notes / approved proof library where applicable | X65: YES — 301 | Y65: Revived content engine — editorial calendar per audit | Revived content engine per editorial calendar. | Z65: DRAFT — HUMAN REVIEW
A66: NUV-P062 | B66: L2 | C66: Offerings | D66: Articles | E66: /articles/ | F66: Architecture L2 | G66: EXISTS | H66: Symptom Aware | I66: Unaware / Problem Aware | J66: Existing content | K66: Read / Explore | M66: /resources/articles/ | O66: =IF(N66="","",LEN(N66)) | Q66: =IF(P66="","",LEN(P66)) | V66: See source notes / approved proof library where applicable | X66: YES — 301 | Y66: Existing content | Z66: DRAFT — HUMAN REVIEW | AA66: Metadata, Schema
A67: NUV-P063 | B67: L2 | C67: Offerings | D67: Podcasts | E67: /podcasts/ | F67: Architecture L2 | G67: EXISTS | H67: Symptom Aware | I67: Unaware / Problem Aware | J67: Existing content | K67: Read / Explore | M67: /resources/podcasts/ | O67: =IF(N67="","",LEN(N67)) | Q67: =IF(P67="","",LEN(P67)) | V67: See source notes / approved proof library where applicable | X67: YES — 301 | Y67: Existing content | Z67: DRAFT — HUMAN REVIEW | AA67: Metadata, Schema
A68: NUV-P064 | B68: L2 | C68: Offerings | D68: Case Studies | F68: Architecture L2 | G68: NEW | H68: Product Aware | J68: Industry-specific with before/after metrics ($400K avg increase) | K68: Explore Related Solution | M68: /resources/case-studies/ | N68: Sales Training Case Studies & Results | NuVue | O68: =IF(N68="","",LEN(N68)) | P68: See how NuVue clients grew revenue with measurable results, including $400K average gains per rep. Real case studies across multiple industries. | Q68: =IF(P68="","",LEN(P68)) | S68: Sales Training Case Studies & Results | T68: CollectionPage, BreadcrumbList | U68: CollectionPage with ItemList of Article items (one per case study). Each: Article (headline, about, image). BreadcrumbList. | V68: See source notes / approved proof library where applicable | X68: NO — new URL | Y68: Industry-specific with before/after metrics ($400K avg increase) | Proof hub. Pioneer, BASF, VA in rough form. | Z68: DRAFT — HUMAN REVIEW
A69: NUV-P065 | B69: L2 | C69: Offerings | D69: Client Testimonials | E69: /testimonials/ | F69: Architecture L2 | G69: EXISTS | H69: Product Aware | J69: Existing content | K69: Explore Related Solution | M69: /resources/testimonials/ | N69: Client Testimonials & Reviews | NuVue | O69: =IF(N69="","",LEN(N69)) | P69: Hear from sales leaders who transformed their teams with NuVue training. Real testimonials on results, ROI, and the Counselor Salesperson method. | Q69: =IF(P69="","",LEN(P69)) | S69: Client Testimonials & Reviews | T69: WebPage, Review, BreadcrumbList | U69: WebPage with Review items (author, reviewBody, itemReviewed=Organization). Consider AggregateRating on the Organization. BreadcrumbList. | V69: See source notes / approved proof library where applicable | X69: YES — 301 | Y69: Existing content | Elevated from buried page. Use only verifiable quotes. | Z69: DRAFT — HUMAN REVIEW
A70: NUV-P066 | B70: L1 | C70: Public Seminars | D70: Public Seminars | E70: /public-seminars/ | F70: Architecture L1 | G70: ENHANCED | H70: Product Aware / Most Aware | I70: Solution Aware | J70: Top-level nav item — dates, pricing ($850-$1,450), Company Name field on forms | K70: Register | L70: Explore Programs | M70: /public-seminars/ | N70: Public Sales Training Seminars & Dates | NuVue | O70: =IF(N70="","",LEN(N70)) | P70: Open-enrollment seminars in consultative selling and negotiation. View upcoming dates and pricing, then register your team for hands-on training. | Q70: =IF(P70="","",LEN(P70)) | S70: Public Sales Training Seminars & Dates | T70: CollectionPage, BreadcrumbList | U70: CollectionPage with ItemList of EducationEvent (name, startDate, endDate, location/virtualLocation, eventAttendanceMode, offers: price/currency). BreadcrumbList. | V70: See source notes / approved proof library where applicable | W70: Registration start; completion; company attribution | X70: NO | Y70: Top-level nav item — dates, pricing ($850-$1,450), Company Name field on forms | Pricing $2,400-$2,800; new ~$1,000 virtual tier under review. Add Company Name field on form. | Z70: DRAFT — HUMAN REVIEW
A71: NUV-P067 | B71: L2 | C71: Public Seminars | D71: Counselor Salesperson | F71: Architecture L2 | G71: NEW | H71: TBD — HUMAN REVIEW | J71: Individual buyer focused public seminar landing page -> select date to purchase | M71: /public-seminars/counselor-salesperson/ | O71: =IF(N71="","",LEN(N71)) | Q71: =IF(P71="","",LEN(P71)) | V71: See source notes / approved proof library where applicable | X71: NO — new URL | Y71: Individual buyer focused public seminar landing page -> select date to purchase | Z71: DRAFT — HUMAN REVIEW | AA71: Buyer intent, Metadata, Schema
A72: NUV-P068 | B72: L2 | C72: Public Seminars | D72: Negotiationg To Yes | F72: Architecture L2 | G72: NEW | H72: TBD — HUMAN REVIEW | J72: Individual buyer focused public seminar landing page -> select date to purchase | M72: /public-seminars/negotiating-to-yes/ | O72: =IF(N72="","",LEN(N72)) | Q72: =IF(P72="","",LEN(P72)) | V72: See source notes / approved proof library where applicable | X72: NO — new URL | Y72: Individual buyer focused public seminar landing page -> select date to purchase | Z72: DRAFT — HUMAN REVIEW | AA72: Buyer intent, Metadata, Schema
A73: NUV-P069 | B73: L2 | C73: Public Seminars | D73: Building Relationship Versatility | F73: Architecture L2 | G73: NEW | H73: TBD — HUMAN REVIEW | J73: Individual buyer focused public seminar landing page -> select date to purchase | M73: /public-seminars/building-relationship-versatility/ | O73: =IF(N73="","",LEN(N73)) | Q73: =IF(P73="","",LEN(P73)) | V73: See source notes / approved proof library where applicable | X73: NO — new URL | Y73: Individual buyer focused public seminar landing page -> select date to purchase | Z73: DRAFT — HUMAN REVIEW | AA73: Buyer intent, Metadata, Schema
A74: NUV-P070 | B74: L1 | C74: About | D74: About NuVue | E74: /about-us/ | F74: Architecture L1 | G74: ENHANCED | H74: Product Aware | I74: Solution Aware | J74: Trust-building section | M74: /about/ | N74: About NuVue | Sales Training Since 2002 | O74: =IF(N74="","",LEN(N74)) | P74: For 24+ years, NuVue has helped companies build high-performing sales and leadership teams. Learn about our approach, our people, and our results. | Q74: =IF(P74="","",LEN(P74)) | S74: About NuVue | Sales Training Since 2002 | T74: AboutPage, Organization, BreadcrumbList | U74: AboutPage referencing the Organization (foundingDate 2002, founder, numberOfEmployees, award, knowsAbout). BreadcrumbList. | V74: See source notes / approved proof library where applicable | X74: YES — 301 | Y74: Trust-building section | Trust signal: 24+ years. E-E-A-T anchor. | Z74: DRAFT — HUMAN REVIEW
A75: NUV-P071 | B75: L2 | C75: About | D75: Our Approach | F75: Architecture L2 | G75: NEW | H75: TBD — HUMAN REVIEW | J75: Methodology depth — LTNS, Wilson Learning, proprietary frameworks, E-E-A-T | M75: /about/our-approach/ | N75: Our Approach to Sales Training | NuVue | O75: =IF(N75="","",LEN(N75)) | P75: NuVue's proven methodology blends consultative selling, behavioral insight, and continuous reinforcement to create lasting performance change. | Q75: =IF(P75="","",LEN(P75)) | S75: Our Approach to Sales Training | T75: AboutPage, BreadcrumbList | U75: AboutPage: name, description, about (methodology), mainEntity. BreadcrumbList. Surface Wilson Learning lineage for E-E-A-T. | V75: See source notes / approved proof library where applicable | X75: NO — new URL | Y75: Methodology depth — LTNS, Wilson Learning, proprietary frameworks, E-E-A-T | Methodology depth page. | Z75: DRAFT — HUMAN REVIEW | AA75: Buyer intent
A76: NUV-P072 | B76: L2 | C76: About | D76: Meet Our Team | E76: /about-us/meet-our-team/ | F76: Architecture L2 | G76: EXISTS | H76: TBD — HUMAN REVIEW | J76: Steve's 35 years + BASF credentials surfaced | M76: /about/team/ | N76: Meet Our Team | NuVue | O76: =IF(N76="","",LEN(N76)) | P76: Meet the NuVue coaches and facilitators behind decades of sales and leadership results, led by founder Steve Rezac and our expert training team. | Q76: =IF(P76="","",LEN(P76)) | S76: Meet Our Team | T76: AboutPage, BreadcrumbList | U76: AboutPage with ItemList of Person (name, jobTitle, image, worksFor, knowsAbout, sameAs). BreadcrumbList. Strong E-E-A-T signal. | V76: See source notes / approved proof library where applicable | X76: YES — 301 | Y76: Steve's 35 years + BASF credentials surfaced | Surface Steve's 35 yrs + BASF credentials. | Z76: DRAFT — HUMAN REVIEW | AA76: Buyer intent
A77: NUV-P073 | B77: L2 | C77: About | D77: Join Our Team | E77: /join-our-team/ | F77: Architecture L2 | G77: EXISTS | H77: TBD — HUMAN REVIEW | J77: Existing page, new URL path | M77: /about/careers/ | O77: =IF(N77="","",LEN(N77)) | Q77: =IF(P77="","",LEN(P77)) | V77: See source notes / approved proof library where applicable | X77: YES — 301 | Y77: Existing page, new URL path | Z77: DRAFT — HUMAN REVIEW | AA77: Buyer intent, Metadata, Schema
A78: NUV-P074 | B78: L1 | C78: About | D78: Request a Consultation | F78: Architecture L1 | G78: NEW | H78: Most Aware | I78: Product Aware | J78: Convert qualified corporate interest into a structured consultation request with usable CRM context. | K78: Submit Consultation Request | M78: /request-consultation/ | N78: Request a Sales Training Consultation | NuVue | O78: =IF(N78="","",LEN(N78)) | P78: Tell us about your team and goals. Request a free consultation to build a tailored sales or leadership training program with measurable ROI. | Q78: =IF(P78="","",LEN(P78)) | S78: Request a Sales Training Consultation | T78: ContactPage, BreadcrumbList | U78: ContactPage: name, description. Reference Organization contactPoint. BreadcrumbList. (Zoho CRM-integrated form.) | V78: See source notes / approved proof library where applicable | W78: Form start; form completion; qualified lead status | X78: NO — new URL | Y78: Primary CTA for corporate buyers — Zoho CRM integration | Primary corporate CTA destination. | Z78: DRAFT — HUMAN REVIEW
A79: NUV-P075 | B79: L1 | C79: About | D79: Apply for the CSP Guarantee | E79: /solutions/sales-enablement/counselor-salesperson-365-guarantee-program-enrollment/ | F79: Architecture L1 | G79: NEW | H79: Most Aware | I79: Product Aware | J79: Qualify enterprise buyers for the CSP Guarantee and route eligible interest into the appropriate sales process. | K79: Apply / Discuss Eligibility | M79: /apply-guarantee/ | N79: Apply for the CSP Performance Guarantee | NuVue | O79: =IF(N79="","",LEN(N79)) | P79: Pay-for-performance sales training: a six-figure revenue gain per rep or you don't pay. Apply to see if your team qualifies for the CSP Guarantee. | Q79: =IF(P79="","",LEN(P79)) | S79: Apply for the CSP Performance Guarantee | T79: WebPage, Offer, BreadcrumbList | U79: WebPage describing the guarantee; Offer/Service (priceSpecification or eligibility via audience: 50+ reps). BreadcrumbList. | V79: See source notes / approved proof library where applicable | W79: Eligibility/application start; completion; qualified status | X79: YES — 301 | Y79: Qualifying application — 100+ reps requirement | Qualifying application. Differentiator - keep claim language verifiable. | Z79: DRAFT — HUMAN REVIEW
A80: NUV-P076 | B80: L1 | C80: About | D80: Contact Us | E80: /contact-us/ | F80: Architecture L1 | G80: EXISTS | H80: TBD — HUMAN REVIEW | J80: Enhanced with Zoho CRM integration | M80: /contact/ | N80: Contact NuVue | Sales Training Experts | O80: =IF(N80="","",LEN(N80)) | P80: Get in touch with NuVue for sales and leadership training, public seminars, or partnership questions. We respond quickly and are glad to help. | Q80: =IF(P80="","",LEN(P80)) | S80: Contact NuVue | Sales Training Experts | T80: ContactPage, Organization, BreadcrumbList | U80: ContactPage with Organization contactPoint (telephone, email, contactType, areaServed, availableLanguage). BreadcrumbList. | V80: See source notes / approved proof library where applicable | X80: YES — 301 | Y80: Enhanced with Zoho CRM integration | Enhanced with Zoho CRM integration. | Z80: DRAFT — HUMAN REVIEW | AA80: Buyer intent
A81: NUV-P077 | B81: L1 | C81: About | D81: Self-Assessment Quiz | F81: Architecture L1 | G81: NEW | H81: Problem Aware | J81: "What's Holding Your Sales Team Back?" — transitional CTA, lead capture | M81: /quiz/ | N81: What's Holding Your Sales Team Back? | NuVue | O81: =IF(N81="","",LEN(N81)) | P81: Take our 2-minute self-assessment to pinpoint what's limiting your sales results, then get tailored training recommendations from NuVue's experts. | Q81: =IF(P81="","",LEN(P81)) | S81: What's Holding Your Sales Team Back? | T81: WebPage, Quiz, BreadcrumbList | U81: WebPage hosting a Quiz (about, educationalAlignment, hasPart: Question/Answer). BreadcrumbList. Transitional CTA + lead capture. | V81: See source notes / approved proof library where applicable | X81: NO — new URL | Y81: "What's Holding Your Sales Team Back?" — transitional CTA, lead capture | Replaces ARA Navigator 360 online. Feeds buyer paths. | Z81: DRAFT — HUMAN REVIEW
A82: NUV-P078 | B82: L1 | C82: About | D82: Thank You / Confirmation | E82: /thank-you/ | F82: Architecture L1 | G82: EXISTS | H82: TBD — HUMAN REVIEW | J82: Post-conversion page | M82: /thank-you/ | O82: =IF(N82="","",LEN(N82)) | Q82: =IF(P82="","",LEN(P82)) | V82: See source notes / approved proof library where applicable | X82: NO | Y82: Post-conversion page | Z82: DRAFT — HUMAN REVIEW | AA82: Buyer intent, Metadata, Schema
A83: NUV-P079 | B83: L1 | C83: About | D83: Store | E83: /store/ | F83: Architecture L1 | G83: ENHANCED | H83: TBD — HUMAN REVIEW | J83: Expanded WooCommerce — seminars, LTNS, curriculum subscriptions | M83: /store/ | O83: =IF(N83="","",LEN(N83)) | Q83: =IF(P83="","",LEN(P83)) | V83: See source notes / approved proof library where applicable | X83: NO | Y83: Expanded WooCommerce — seminars, LTNS, curriculum subscriptions | Z83: DRAFT — HUMAN REVIEW | AA83: Buyer intent, Metadata, Schema
A84: NUV-P080 | B84: L1 | C84: About | D84: Cart | E84: /cart/ | F84: Architecture L1 | G84: EXISTS | H84: TBD — HUMAN REVIEW | J84: Existing | M84: /cart/ | O84: =IF(N84="","",LEN(N84)) | Q84: =IF(P84="","",LEN(P84)) | V84: See source notes / approved proof library where applicable | X84: NO | Y84: Existing | Z84: DRAFT — HUMAN REVIEW | AA84: Buyer intent, Metadata, Schema
A85: NUV-P081 | B85: L1 | C85: About | D85: Checkout | E85: /checkout/ | F85: Architecture L1 | G85: EXISTS | H85: TBD — HUMAN REVIEW | J85: Existing | M85: /checkout/ | O85: =IF(N85="","",LEN(N85)) | Q85: =IF(P85="","",LEN(P85)) | V85: See source notes / approved proof library where applicable | X85: NO | Y85: Existing | Z85: DRAFT — HUMAN REVIEW | AA85: Buyer intent, Metadata, Schema
A86: NUV-P082 | B86: L1 | C86: About | D86: My Account | E86: /my-account/ | F86: Architecture L1 | G86: EXISTS | H86: TBD — HUMAN REVIEW | J86: Existing | M86: /my-account/ | O86: =IF(N86="","",LEN(N86)) | Q86: =IF(P86="","",LEN(P86)) | V86: See source notes / approved proof library where applicable | X86: NO | Y86: Existing | Z86: DRAFT — HUMAN REVIEW | AA86: Buyer intent, Metadata, Schema
A87: NUV-P083 | B87: L1 | C87: About | D87: My Bookings | E87: /my-bookings/ | F87: Architecture L1 | G87: EXISTS | H87: TBD — HUMAN REVIEW | J87: Existing | M87: /my-bookings/ | O87: =IF(N87="","",LEN(N87)) | Q87: =IF(P87="","",LEN(P87)) | V87: See source notes / approved proof library where applicable | X87: NO | Y87: Existing | Z87: DRAFT — HUMAN REVIEW | AA87: Buyer intent, Metadata, Schema
A88: NUV-P084 | B88: L1 | C88: About | D88: Privacy Policy | E88: /privacy-policy/ | F88: Architecture L1 | G88: EXISTS | H88: TBD — HUMAN REVIEW | J88: Existing | M88: /privacy-policy/ | O88: =IF(N88="","",LEN(N88)) | Q88: =IF(P88="","",LEN(P88)) | V88: See source notes / approved proof library where applicable | X88: NO | Y88: Existing | Z88: DRAFT — HUMAN REVIEW | AA88: Buyer intent, Metadata, Schema
A89: NUV-P085 | B89: L1 | C89: About | D89: Communication Preferences | E89: /communication-preferences/ | F89: Architecture L1 | G89: EXISTS | H89: TBD — HUMAN REVIEW | J89: Existing | M89: /communication-preferences/ | O89: =IF(N89="","",LEN(N89)) | Q89: =IF(P89="","",LEN(P89)) | V89: See source notes / approved proof library where applicable | X89: NO | Y89: Existing | Z89: DRAFT — HUMAN REVIEW | AA89: Buyer intent, Metadata, Schema
A90: NUV-P086 | B90: L1 | C90: Pages To Hide From Navigation | D90: Learning That Never Stops® Sign Up | E90: /learning-that-never-stops-signup/ | F90: Architecture L1 | G90: EXISTS | H90: TBD — HUMAN REVIEW | J90: Repositioned as retention & expansion tool, not just reinforcement | O90: =IF(N90="","",LEN(N90)) | Q90: =IF(P90="","",LEN(P90)) | V90: See source notes / approved proof library where applicable | Y90: Repositioned as retention & expansion tool, not just reinforcement | Z90: DRAFT — HUMAN REVIEW | AA90: Buyer intent, Metadata, Schema
A91: NUV-P087 | B91: L1 | C91: Pages To Hide From Navigation | D91: Westlink 6th Man | E91: /westlink6thman/ | F91: Architecture L1 | G91: EXISTS | H91: TBD — HUMAN REVIEW | J91: Campaign-specific — archive or redirect | O91: =IF(N91="","",LEN(N91)) | Q91: =IF(P91="","",LEN(P91)) | V91: See source notes / approved proof library where applicable | Y91: Campaign-specific — archive or redirect | Z91: DRAFT — HUMAN REVIEW | AA91: Buyer intent, Metadata, Schema
A92: NUV-P088 | B92: L1 | C92: Pages To Hide From Navigation | D92: Marketing Signup | E92: /marketingsignup/ | F92: Architecture L1 | G92: EXISTS | H92: TBD — HUMAN REVIEW | J92: Replace with new conversion pages | O92: =IF(N92="","",LEN(N92)) | Q92: =IF(P92="","",LEN(P92)) | V92: See source notes / approved proof library where applicable | Y92: Replace with new conversion pages | Z92: DRAFT — HUMAN REVIEW | AA92: Buyer intent, Metadata, Schema
A93: NUV-P089 | B93: L1 | C93: Pages To Hide From Navigation | D93: CSP Training Landing Page | E93: /counselor-salesperson-training-landing-page-contact-form/ | F93: Architecture L1 | G93: EXISTS | H93: TBD — HUMAN REVIEW | J93: Replace with new CSP page structure | O93: =IF(N93="","",LEN(N93)) | Q93: =IF(P93="","",LEN(P93)) | V93: See source notes / approved proof library where applicable | Y93: Replace with new CSP page structure | Z93: DRAFT — HUMAN REVIEW | AA93: Buyer intent, Metadata, Schema
A94: NUV-P090 | B94: L1 | C94: Pages To Retire / Redirect | D94: Public Seminars 2 (duplicate) | E94: /public-seminars-2/ | F94: Architecture L1 | G94: RETIRE | H94: Product Aware / Most Aware | I94: Solution Aware | J94: Redirect to /public-seminars/ | K94: Register | L94: Explore Programs | O94: =IF(N94="","",LEN(N94)) | Q94: =IF(P94="","",LEN(P94)) | V94: See source notes / approved proof library where applicable | W94: Registration start; completion; company attribution | X94: YES — target required | Y94: Redirect to /public-seminars/ | Z94: DRAFT — HUMAN REVIEW | AA94: Redirect target
A95: NUV-P091 | B95: L1 | C95: Pages To Retire / Redirect | D95: Customer Service section | E95: /solutions/customer-service/ | F95: Architecture L1 | G95: RETIRE | H95: N/A — RETIRE | J95: Programs absorbed into Sales Development or Leadership pillars | O95: =IF(N95="","",LEN(N95)) | Q95: =IF(P95="","",LEN(P95)) | V95: See source notes / approved proof library where applicable | X95: YES — target required | Y95: Programs absorbed into Sales Development or Leadership pillars | Z95: DRAFT — HUMAN REVIEW | AA95: Redirect target
A96: NUV-P092 | B96: L1 | C96: Pages To Retire / Redirect | D96: Coaching | E96: /solutions/coaching/ | F96: Architecture L1 | G96: RETIRE | H96: N/A — RETIRE | J96: Programs moved to Leadership pillar | O96: =IF(N96="","",LEN(N96)) | Q96: =IF(P96="","",LEN(P96)) | V96: See source notes / approved proof library where applicable | X96: YES — target required | Y96: Programs moved to Leadership pillar | Z96: DRAFT — HUMAN REVIEW | AA96: Redirect target
A97: NUV-P093 | B97: L2 | C97: Pages To Retire / Redirect | D97: Sales Curriculum Guide | E97: /sales-curriculum/ | F97: Architecture L2 | G97: RETIRE | H97: N/A — RETIRE | J97: Moved from top-level to Resources section | K97: Explore Relevant Solution | L97: Request a Consultation | O97: =IF(N97="","",LEN(N97)) | Q97: =IF(P97="","",LEN(P97)) | V97: See source notes / approved proof library where applicable | X97: YES — target required | Y97: Moved from top-level to Resources section | Z97: DRAFT — HUMAN REVIEW | AA97: Redirect target
A98: NUV-P094 | B98: L1 | C98: Pages To Retire / Redirect | D98: eLearning section | E98: /solutions/elearning/ | F98: Architecture L1 | G98: RETIRE | H98: N/A — RETIRE | J98: Programs moved to LTNS hub | O98: =IF(N98="","",LEN(N98)) | Q98: =IF(P98="","",LEN(P98)) | V98: See source notes / approved proof library where applicable | X98: YES — target required | Y98: Programs moved to LTNS hub | Z98: DRAFT — HUMAN REVIEW | AA98: Redirect target
A99: NUV-P095 | B99: L1 | C99: Pages To Retire / Redirect | D99: Events | E99: /events/ | F99: Architecture L1 | G99: RETIRE | H99: N/A — RETIRE | J99: Replaced by Public Seminars | O99: =IF(N99="","",LEN(N99)) | Q99: =IF(P99="","",LEN(P99)) | V99: See source notes / approved proof library where applicable | X99: YES — target required | Y99: Replaced by Public Seminars | Z99: DRAFT — HUMAN REVIEW | AA99: Redirect target
A100: NUV-P096 | B100: L1 | C100: Pages To Retire / Redirect | D100: Logos | E100: /logos/ | F100: Architecture L1 | G100: RETIRE | H100: N/A — RETIRE | J100: Internal page — remove from public nav | O100: =IF(N100="","",LEN(N100)) | Q100: =IF(P100="","",LEN(P100)) | V100: See source notes / approved proof library where applicable | X100: YES — target required | Y100: Internal page — remove from public nav | Z100: DRAFT — HUMAN REVIEW | AA100: Redirect target
A101: NUV-P097 | B101: L1 | C101: Pages To Retire / Redirect | D101: Locations | E101: /locations/ | F101: Architecture L1 | G101: RETIRE | H101: N/A — RETIRE | J101: Low-value page | O101: =IF(N101="","",LEN(N101)) | Q101: =IF(P101="","",LEN(P101)) | V101: See source notes / approved proof library where applicable | X101: YES — target required | Y101: Low-value page | Z101: DRAFT — HUMAN REVIEW | AA101: Redirect target
A102: NUV-P098 | B102: L1 | C102: Pages To Retire / Redirect | D102: Categories | E102: /categories/ | F102: Architecture L1 | G102: RETIRE | H102: N/A — RETIRE | J102: WP default — not needed | O102: =IF(N102="","",LEN(N102)) | Q102: =IF(P102="","",LEN(P102)) | V102: See source notes / approved proof library where applicable | X102: YES — target required | Y102: WP default — not needed | Z102: DRAFT — HUMAN REVIEW | AA102: Redirect target
...

Sheet Navigation
A1: Navigation
A2: Proposed NuVue navigation context carried forward from the source architecture. Human review required before implementation.
A4: Nav Tier | B4: Level 1 | C4: Level 2 | D4: Level 3 | E4: URL | F4: Template Qty | G4: Content Qty | H4: Notes | I4: Approval Status
A5: Primary | B5: For Organizations | E5: /solutions-for-organizations/ | F5: 1 | H5: Search filters for programs/courses by curriculum, search bar, delivery type, level | I5: DRAFT — HUMAN REVIEW
A6: Primary | B6: For Individuals | E6: /solutions-for-professionals/ | G6: 1 | I6: DRAFT — HUMAN REVIEW
A7: Primary | B7: Industries | E7: /industries/ | I7: DRAFT — HUMAN REVIEW
A8: Primary | C8: Agriculture | E8: /industries/agriculture/ | F8: 1 | G8: 5 | H8: Ag Sales Onboarding | I8: DRAFT — HUMAN REVIEW
A9: Primary | C9: Manufacturing | E9: /industries/manufacturing/ | I9: DRAFT — HUMAN REVIEW
A10: Primary | C10: Insurance & Financial Services | E10: /industries/insurance-financial-services/ | I10: DRAFT — HUMAN REVIEW
A11: Primary | C11: Turf & Horticulture | E11: /industries/turf-horticulture/ | I11: DRAFT — HUMAN REVIEW
A12: Primary | C12: Sales & Services | E12: /industries/sales-and-services/ | I12: DRAFT — HUMAN REVIEW
A13: Primary | C13: Healthcare, Science & Biotech | E13: /industries/healthcare-science-biotech/ | I13: DRAFT — HUMAN REVIEW
A14: Primary | B14: Programs | F14: 1 | H14: New post type (in place of solutions) for easier search/filter | I14: DRAFT — HUMAN REVIEW
A15: Primary | C15: Sales & Leadership Curriculums | E15: /curriculum/ | G15: 3 | H15: Curriculum filter page | I15: DRAFT — HUMAN REVIEW
A16: Primary | D16: Sales Curriculum Post | F16: 1 | G16: 18 | H16: number based off curriculum diagram | I16: DRAFT — HUMAN REVIEW
A17: Primary | D17: Leadership Curriculum Post | G17: 18 | I17: DRAFT — HUMAN REVIEW
A18: Primary | D18: Business Acumen Post | G18: 4 | I18: DRAFT — HUMAN REVIEW
A19: Primary | C19: Public Seminars | G19: 2 | I19: DRAFT — HUMAN REVIEW
A20: Primary | D20: Counselor Salesperson | E20: /public-seminars/counselor-salesperson/ | F20: 1 | I20: DRAFT — HUMAN REVIEW
A21: Primary | D21: Negotiationg To Yes | E21: /public-seminars/negotiating-to-yes/ | I21: DRAFT — HUMAN REVIEW
A22: Primary | D22: Building Relationship Versatility | E22: /public-seminars/building-relationship-versatility/ | I22: DRAFT — HUMAN REVIEW
A23: Primary | C23: Team Building | G23: 1 | I23: DRAFT — HUMAN REVIEW
A24: Primary | C24: Executive Coaching | G24: 1 | I24: DRAFT — HUMAN REVIEW
A25: Primary | B25: Resources | E25: /resources/ | F25: 1 | H25: Resource filter page | I25: DRAFT — HUMAN REVIEW
A26: Primary | C26: Assessments | E26: /resources/assessments/ | G26: 1 | H26: (Lead magnet) | I26: DRAFT — HUMAN REVIEW
A27: Primary | C27: Blog | E27: /resources/blog/ | G27: 1 | I27: DRAFT — HUMAN REVIEW
A28: Primary | C28: Articles | E28: /resources/articles/ | G28: 1 | I28: DRAFT — HUMAN REVIEW
A29: Primary | C29: Podcasts | E29: /resources/podcasts/ | G29: 1 | I29: DRAFT — HUMAN REVIEW
A30: Primary | C30: Case Studies | E30: /resources/case-studies/ | F30: 1 | G30: 1 | I30: DRAFT — HUMAN REVIEW
A31: Primary | C31: Client Testimonials | E31: /resources/testimonials/ | G31: 1 | I31: DRAFT — HUMAN REVIEW
A32: Primary | B32: Request Consultation [Primary CTA] | E32: /request-consultation/ | F32: 1 | I32: DRAFT — HUMAN REVIEW
A33: Primary | B33: Cart icon | E33: /cart/ | I33: DRAFT — HUMAN REVIEW
A34: Footer | B34: Home | E34: / | I34: DRAFT — HUMAN REVIEW
A35: Footer | B35: About | E35: /about-us/ | F35: 1 | I35: DRAFT — HUMAN REVIEW
A36: Footer | C36: Approach | E36: /about-us/approach/ | F36: 1 | G36: 1 | I36: DRAFT — HUMAN REVIEW
A37: Footer | C37: Team | E37: /about-us/team/ | G37: 1 | I37: DRAFT — HUMAN REVIEW
A38: Footer | C38: Join our team | E38: /about-us/join-our-team/ | G38: 1 | I38: DRAFT — HUMAN REVIEW
A39: Footer | B39: Contact | E39: /contact/ | G39: 1 | I39: DRAFT — HUMAN REVIEW

Sheet Redirects
A1: Redirects
A2: Migration map generated from existing vs. proposed URLs. Retired pages without an approved target remain unresolved.
A4: # | B4: Page ID | C4: Existing URL | D4: 301 Target | E4: Type | F4: Reason | G4: Status | H4: Owner
A5: 1 | B5: NUV-P004 | C5: /solutions/ | D5: /curriculum/ | E5: 301 | F5: RESTRUCTURED: URL changes in proposed architecture. | G5: DRAFT — HUMAN REVIEW | H5: SimpliCreative → NuVue approves
A6: 2 | B6: NUV-P005 | C6: /solutions/sales-enablement/ | D6: /curriculum/sales/ | E6: 301 | F6: RESTRUCTURED: URL changes in proposed architecture. | G6: DRAFT — HUMAN REVIEW | H6: SimpliCreative → NuVue approves
A7: 3 | B7: NUV-P006 | C7: /solutions/sales-enablement/counselor-salesperson/ | D7: /curriculum/sales/counselor-salesperson/ | E7: 301 | F7: ENHANCED: URL changes in proposed architecture. | G7: DRAFT — HUMAN REVIEW | H7: SimpliCreative → NuVue approves
A8: 4 | B8: NUV-P007 | C8: /solutions/sales-enablement/counselor-prospecting/ | D8: /curriculum/sales/counselor-prospecting/ | E8: 301 | F8: EXISTS: URL changes in proposed architecture. | G8: DRAFT — HUMAN REVIEW | H8: SimpliCreative → NuVue approves
A9: 5 | B9: NUV-P008 | C9: /solutions/sales-enablement/selling-in-a-virtual-environment/ | D9: /curriculum/sales/selling-in-a-virtual-environment/ | E9: 301 | F9: EXISTS: URL changes in proposed architecture. | G9: DRAFT — HUMAN REVIEW | H9: SimpliCreative → NuVue approves
A10: 6 | B10: NUV-P009 | C10: /solutions/sales-enablement/mastering-successful-presentations-skills-for-influencing-outcomes/ | D10: /curriculum/sales/presentations/ | E10: 301 | F10: EXISTS: URL changes in proposed architecture. | G10: DRAFT — HUMAN REVIEW | H10: SimpliCreative → NuVue approves
A11: 7 | B11: NUV-P010 | C11: /solutions/sales-enablement/versatile-salesperson/ | D11: /curriculum/sales/versatile-salesperson/ | E11: 301 | F11: EXISTS: URL changes in proposed architecture. | G11: DRAFT — HUMAN REVIEW | H11: SimpliCreative → NuVue approves
A12: 8 | B12: NUV-P011 | C12: /solutions/sales-enablement/selling-to-the-generations/ | D12: /curriculum/sales/selling-to-the-generations/ | E12: 301 | F12: EXISTS: URL changes in proposed architecture. | G12: DRAFT — HUMAN REVIEW | H12: SimpliCreative → NuVue approves
A13: 9 | B13: NUV-P012 | C13: /solutions/sales-enablement/turning-information-into-sales/ | D13: /curriculum/sales/turning-information-into-sales/ | E13: 301 | F13: EXISTS: URL changes in proposed architecture. | G13: DRAFT — HUMAN REVIEW | H13: SimpliCreative → NuVue approves
A14: 10 | B14: NUV-P013 | C14: /solutions/sales-enablement/negotiating-to-yes-sales-edition/ | D14: /curriculum/sales/negotiating-to-yes/ | E14: 301 | F14: EXISTS: URL changes in proposed architecture. | G14: DRAFT — HUMAN REVIEW | H14: SimpliCreative → NuVue approves
A15: 11 | B15: NUV-P014 | C15: /solutions/sales-enablement/time-management-for-salespeople/ | D15: /curriculum/sales/time-management/ | E15: 301 | F15: EXISTS: URL changes in proposed architecture. | G15: DRAFT — HUMAN REVIEW | H15: SimpliCreative → NuVue approves
A16: 12 | B16: NUV-P015 | C16: /solutions/sales-enablement/coaching-the-counselor-salesperson/ | D16: /curriculum/sales/coaching-the-counselor-salesperson/ | E16: 301 | F16: EXISTS: URL changes in proposed architecture. | G16: DRAFT — HUMAN REVIEW | H16: SimpliCreative → NuVue approves
... A78: 74 | B78: NUV-P099 | C78: /tags/ | D78: TBD — HUMAN APPROVAL | E78: 301 / retire | F78: Retired page requires an approved destination based on relevance and equity. | G78: OPEN | H78: SimpliCreative → NuVue approves

Sheet Schema Guide
A1: Schema Implementation Guide
A2: Reusable schema guidance. Page-specific schema assignments remain on the Sitemap tab.
A4: Schema Type | B4: When to Use on NuVue | C4: Key Properties to Populate | D4: Implementation Rule
A5: Organization | B5: Sitewide, in the <head> of every page (output once via theme/SEO plugin). | C5: name, url, logo, description, foundingDate (2002), founder (Steve Rezac), sameAs (LinkedIn + socials), contactPoint, areaServed, knowsAbout, award. | D5: Use only when the actual page content supports the schema type. Missing content is a content gap, not a markup problem.
A6: WebSite | B6: Sitewide, alongside Organization. Enables sitelinks search box. | C6: name, url, publisher (Organization), potentialAction → SearchAction with target + query-input. | D6: Use only when the actual page content supports the schema type. Missing content is a content gap, not a markup problem.
A7: BreadcrumbList | B7: Every page except the homepage. Mirrors the URL hierarchy. | C7: itemListElement: ordered ListItem entries (position, name, item URL). | D7: Use only when the actual page content supports the schema type. Missing content is a content gap, not a markup problem.
A8: CollectionPage | B8: Hub/landing pages that list children: Curriculum Overview, each pillar, Industries hub, Resources, Case Studies. | C8: name, description, isPartOf, mainEntity/hasPart → ItemList of the child pages. | D8: Use only when the actual page content supports the schema type. Missing content is a content gap, not a markup problem.
A9: Course | B9: Scheduled, multi-attendee training programs: CSP, Income|Outcome, individual workshops. | C9: name, description, provider (Organization), educationalLevel, hasCourseInstance (courseMode: onsite/online/blended, courseWorkload, location), optional offers. | D9: Use only when the actual page content supports the schema type. Missing content is a content gap, not a markup problem.
A10: Service | B10: 1:1 or industry offerings that are not scheduled courses: Executive Coaching, For Organizations, For Sales Professionals, all Industry pages. | C10: serviceType, provider, areaServed, audience (BusinessAudience or Audience), optional offers/priceSpecification. | D10: Use only when the actual page content supports the schema type. Missing content is a content gap, not a markup problem.
A11: Blog / BlogPosting | B11: Blog index uses Blog; each article uses BlogPosting. | C11: Blog: name, description, publisher. BlogPosting: headline, author (Person), datePublished, dateModified, image, mainEntityOfPage. | D11: Use only when the actual page content supports the schema type. Missing content is a content gap, not a markup problem.
A12: AboutPage | B12: About NuVue, Our Approach, Meet Our Team. | C12: name, description, about; reference Organization. Meet Our Team adds ItemList of Person (name, jobTitle, image, knowsAbout, sameAs). | D12: Use only when the actual page content supports the schema type. Missing content is a content gap, not a markup problem.
A13: ContactPage | B13: Contact Us, Request a Consultation. | C13: name, description; reference Organization contactPoint (telephone, email, contactType, areaServed, availableLanguage). | D13: Use only when the actual page content supports the schema type. Missing content is a content gap, not a markup problem.
A14: Review / AggregateRating | B14: Client Testimonials, and aggregate rating on the Organization. | C14: Review: author, reviewBody, itemReviewed, reviewRating. AggregateRating: ratingValue, reviewCount. Use only verifiable, attributable quotes. | D14: Use only when the actual page content supports the schema type. Missing content is a content gap, not a markup problem.
A15: EducationEvent | B15: Each dated session on Public Seminars. | C15: name, startDate, endDate, eventAttendanceMode, location or virtualLocation, offers (price, priceCurrency, availability, url). | D15: Use only when the actual page content supports the schema type. Missing content is a content gap, not a markup problem.
... A17: FAQPage | B17: Optional, add to any page with a genuine Q&A block (e.g. Assessments, program pages). | C17: mainEntity → Question + acceptedAnswer (Answer). Only mark up Q&A visible on the page. | D17: Use only when the actual page content supports the schema type. Missing content is a content gap, not a markup problem.
A18: Implementation notes: Use JSON-LD (Google's preferred format). Output one @graph per page combining the sitewide entities (Organization, WebSite) with the page-specific type(s). Validate every template in Google's Rich Results Test and Schema.org validator before launch. Keep all marked-up claims (ratings, results, guarantees) factual and matched to on-page content. | D18: Use only when the actual page content supports the schema type. Missing content is a content gap, not a markup problem.

Sheet Authority & Proof
A1: Authority & Proof Requirements
A2: Optional supporting map for page-level credibility, proof, expertise, and authority requirements.
A4: Signal / Requirement | B4: Page(s) | C4: What Must Be True | D4: Evidence / Source Needed | E4: Schema / Implementation Tie | F4: Status | G4: Owner
A5: Enterprise proof visible where evaluation happens | B5: Homepage; For Organizations; Results; priority solution pages | C5: Approved logos, case evidence, testimonials, and ROI evidence appear near the buyer questions they support. | D5: Logo permissions; ROI Impact Evaluations; approved case studies | E5: Organization / Review / Service properties where valid | F5: OPEN | G5: NuVue + SimpliCreative
A6: Learning That Never Stops® is explained as a real methodology | B6: Homepage; How We Work; priority program pages | C6: The site explains reinforcement and continued application, not merely the trademark name. | D6: Approved methodology description; current program support details | E6: Service / Course / WebPage context as applicable | F6: DRAFT | G6: NuVue + SimpliCreative
A7: Guarantee is qualified and evidence-backed | B7: Homepage teaser; CSP Guarantee page | C7: Eligibility, terms, completion requirements, annual capacity, and supporting proof are current and explicit. | D7: Current guarantee documentation; eligibility rules; ROI methodology | E7: Service / Offer properties only where supported | F7: OPEN | G7: NuVue
A8: Industry expertise is specific rather than generic | B8: Agriculture; Manufacturing; Insurance pages | C8: Industry pages include real language, use cases, proof, and relevant programs rather than swapped industry labels. | D8: Client examples; industry-specific content; program mapping | E8: Service / CollectionPage / Article as appropriate | F8: OPEN | G8: NuVue + SimpliCreative
A9: NuVue authorship and expertise are clear | B9: About; Resources; thought leadership | C9: Author / organization expertise is visible and traceable. | D9: Team bios; credentials; authorship rules; external profiles | E9: Person / Organization / Article properties where valid | F9: OPEN | G9: NuVue

Sheet Summary
A1: Architecture Summary
A2: Formula-driven view of page scope, metadata/schema completeness, and unresolved review items.
A4: Metric | B4: Formula / Result | C4: Purpose
A5: Total page records | B5: =COUNTA(Sitemap!D5:D103) | C5: All active and retire architecture records
A6: New pages | B6: =COUNTIF(Sitemap!G5:G103,"NEW") | C6: Brand-new pages
A7: Enhanced pages | B7: =COUNTIF(Sitemap!G5:G103,"ENHANCED") | C7: Existing pages with significant change
A8: Restructured pages | B8: =COUNTIF(Sitemap!G5:G103,"RESTRUCTURED") | C8: Pages reorganized into new hierarchy
A9: Retire pages | B9: =COUNTIF(Sitemap!G5:G103,"RETIRE") | C9: Pages proposed for retirement
A10: Pages with meta title | B10: =COUNTIF(Sitemap!N5:N103,"<>") | C10: Metadata coverage
A11: Pages with schema | B11: =COUNTIF(Sitemap!T5:T103,"<>") | C11: Schema coverage
A12: Pages needing review | B12: =COUNTIF(Sitemap!AA5:AA103,"<>") | C12: Rows with unresolved review flags
A13: Redirect records | B13: =COUNTA(Redirects!C5:C78) | C13: URL changes / retirements requiring migration handling

Sheet Change Log
A1: Change Log
A2: Revision tracking for the Integrated Site Architecture workbook.
A4: Version | B4: Date | C4: Requested By | D4: Tab | E4: Page / Item | F4: Change | G4: Status | H4: Approved By
A5: v1.0 | B5: 2026-09-02 | C5: SimpliCreative | D5: All | E5: Initial Gold Standard | F5: Combined NuVue Proposed Site Architecture and Meta & Schema Recommendations into one integrated Foundation workbook; added buyer intent, proof/measurement fields, redirects, review flags, and governing rules. | G5: Issued for Human Review
